{
  "schema": [
    {
      "name": "<DBEA0DF4>",
      "type": 9
    },
    {
      "name": "<A815E3A7>",
      "type": 2
    },
    {
      "name": "<03053E2C>",
      "type": 2
    },
    {
      "name": "<E04C8806>",
      "type": 2
    },
    {
      "name": "<5DDB3CD8>",
      "type": 2
    },
    {
      "name": "<4EC0BC69>",
      "type": 2
    },
    {
      "name": "<7D1DE80F>",
      "type": 2
    },
    {
      "name": "<B138A4D8>",
      "type": 2
    },
    {
      "name": "<CF46B266>",
      "type": 2
    },
    {
      "name": "<78873410>",
      "type": 2
    },
    {
      "name": "<532A2A64>",
      "type": 2
    },
    {
      "name": "<E64DCC48>",
      "type": 2
    },
    {
      "name": "<F6B044EE>",
      "type": 2
    },
    {
      "name": "<52603A9C>",
      "type": 2
    }
  ],
  "rows": [
    {
      "$id": 1,
      "<DBEA0DF4>": "<0E6A0ECB>",
      "<A815E3A7>": 26,
      "<03053E2C>": 287,
      "<E04C8806>": 544,
      "<5DDB3CD8>": 807,
      "<4EC0BC69>": 1065,
      "<7D1DE80F>": 1324,
      "<B138A4D8>": 1584,
      "<CF46B266>": 1847,
      "<78873410>": 2137,
      "<532A2A64>": 2403,
      "<E64DCC48>": 2664,
      "<F6B044EE>": 2921,
      "<52603A9C>": 0
    },
    {
      "$id": 2,
      "<DBEA0DF4>": "<B0DD8DD7>",
      "<A815E3A7>": 27,
      "<03053E2C>": 288,
      "<E04C8806>": 545,
      "<5DDB3CD8>": 808,
      "<4EC0BC69>": 1066,
      "<7D1DE80F>": 1325,
      "<B138A4D8>": 1585,
      "<CF46B266>": 1848,
      "<78873410>": 2138,
      "<532A2A64>": 2404,
      "<E64DCC48>": 2665,
      "<F6B044EE>": 2922,
      "<52603A9C>": 0
    },
    {
      "$id": 3,
      "<DBEA0DF4>": "<11D2EAD6>",
      "<A815E3A7>": 28,
      "<03053E2C>": 289,
      "<E04C8806>": 546,
      "<5DDB3CD8>": 809,
      "<4EC0BC69>": 1067,
      "<7D1DE80F>": 1326,
      "<B138A4D8>": 1586,
      "<CF46B266>": 1849,
      "<78873410>": 2139,
      "<532A2A64>": 2405,
      "<E64DCC48>": 2666,
      "<F6B044EE>": 2923,
      "<52603A9C>": 0
    },
    {
      "$id": 4,
      "<DBEA0DF4>": "<74026695>",
      "<A815E3A7>": 29,
      "<03053E2C>": 290,
      "<E04C8806>": 547,
      "<5DDB3CD8>": 810,
      "<4EC0BC69>": 1068,
      "<7D1DE80F>": 1327,
      "<B138A4D8>": 1587,
      "<CF46B266>": 1850,
      "<78873410>": 2140,
      "<532A2A64>": 2406,
      "<E64DCC48>": 2667,
      "<F6B044EE>": 2924,
      "<52603A9C>": 0
    },
    {
      "$id": 5,
      "<DBEA0DF4>": "<589CA3FC>",
      "<A815E3A7>": 30,
      "<03053E2C>": 291,
      "<E04C8806>": 548,
      "<5DDB3CD8>": 811,
      "<4EC0BC69>": 1069,
      "<7D1DE80F>": 1328,
      "<B138A4D8>": 1588,
      "<CF46B266>": 1851,
      "<78873410>": 2141,
      "<532A2A64>": 2407,
      "<E64DCC48>": 2668,
      "<F6B044EE>": 2925,
      "<52603A9C>": 0
    },
    {
      "$id": 6,
      "<DBEA0DF4>": "<6CD761C7>",
      "<A815E3A7>": 31,
      "<03053E2C>": 292,
      "<E04C8806>": 549,
      "<5DDB3CD8>": 812,
      "<4EC0BC69>": 1070,
      "<7D1DE80F>": 1329,
      "<B138A4D8>": 1589,
      "<CF46B266>": 1852,
      "<78873410>": 2142,
      "<532A2A64>": 2408,
      "<E64DCC48>": 2669,
      "<F6B044EE>": 2926,
      "<52603A9C>": 0
    },
    {
      "$id": 7,
      "<DBEA0DF4>": "<1E102E7E>",
      "<A815E3A7>": 32,
      "<03053E2C>": 293,
      "<E04C8806>": 550,
      "<5DDB3CD8>": 813,
      "<4EC0BC69>": 1071,
      "<7D1DE80F>": 1330,
      "<B138A4D8>": 1590,
      "<CF46B266>": 1853,
      "<78873410>": 2143,
      "<532A2A64>": 2409,
      "<E64DCC48>": 2670,
      "<F6B044EE>": 2927,
      "<52603A9C>": 0
    },
    {
      "$id": 8,
      "<DBEA0DF4>": "<6F318DE7>",
      "<A815E3A7>": 33,
      "<03053E2C>": 294,
      "<E04C8806>": 551,
      "<5DDB3CD8>": 814,
      "<4EC0BC69>": 1072,
      "<7D1DE80F>": 1331,
      "<B138A4D8>": 1591,
      "<CF46B266>": 1854,
      "<78873410>": 2144,
      "<532A2A64>": 2410,
      "<E64DCC48>": 2671,
      "<F6B044EE>": 2928,
      "<52603A9C>": 0
    },
    {
      "$id": 9,
      "<DBEA0DF4>": "<0A7A5A93>",
      "<A815E3A7>": 34,
      "<03053E2C>": 295,
      "<E04C8806>": 552,
      "<5DDB3CD8>": 815,
      "<4EC0BC69>": 1073,
      "<7D1DE80F>": 1332,
      "<B138A4D8>": 1592,
      "<CF46B266>": 1855,
      "<78873410>": 2145,
      "<532A2A64>": 2411,
      "<E64DCC48>": 2672,
      "<F6B044EE>": 2929,
      "<52603A9C>": 0
    },
    {
      "$id": 10,
      "<DBEA0DF4>": "<77CF4416>",
      "<A815E3A7>": 35,
      "<03053E2C>": 296,
      "<E04C8806>": 553,
      "<5DDB3CD8>": 816,
      "<4EC0BC69>": 1074,
      "<7D1DE80F>": 1333,
      "<B138A4D8>": 1593,
      "<CF46B266>": 1856,
      "<78873410>": 2146,
      "<532A2A64>": 2412,
      "<E64DCC48>": 2673,
      "<F6B044EE>": 2930,
      "<52603A9C>": 0
    },
    {
      "$id": 11,
      "<DBEA0DF4>": "<9FC0B833>",
      "<A815E3A7>": 36,
      "<03053E2C>": 297,
      "<E04C8806>": 554,
      "<5DDB3CD8>": 817,
      "<4EC0BC69>": 1075,
      "<7D1DE80F>": 1334,
      "<B138A4D8>": 1594,
      "<CF46B266>": 1857,
      "<78873410>": 2147,
      "<532A2A64>": 2413,
      "<E64DCC48>": 2674,
      "<F6B044EE>": 2931,
      "<52603A9C>": 0
    },
    {
      "$id": 12,
      "<DBEA0DF4>": "<E12F949F>",
      "<A815E3A7>": 37,
      "<03053E2C>": 298,
      "<E04C8806>": 555,
      "<5DDB3CD8>": 818,
      "<4EC0BC69>": 1076,
      "<7D1DE80F>": 1335,
      "<B138A4D8>": 1595,
      "<CF46B266>": 1858,
      "<78873410>": 2148,
      "<532A2A64>": 2414,
      "<E64DCC48>": 2675,
      "<F6B044EE>": 2932,
      "<52603A9C>": 0
    },
    {
      "$id": 13,
      "<DBEA0DF4>": "<FDCEDAC2>",
      "<A815E3A7>": 38,
      "<03053E2C>": 299,
      "<E04C8806>": 556,
      "<5DDB3CD8>": 819,
      "<4EC0BC69>": 1077,
      "<7D1DE80F>": 1336,
      "<B138A4D8>": 1596,
      "<CF46B266>": 1859,
      "<78873410>": 2149,
      "<532A2A64>": 2415,
      "<E64DCC48>": 2676,
      "<F6B044EE>": 2933,
      "<52603A9C>": 0
    },
    {
      "$id": 14,
      "<DBEA0DF4>": "<4C6741C4>",
      "<A815E3A7>": 39,
      "<03053E2C>": 300,
      "<E04C8806>": 557,
      "<5DDB3CD8>": 820,
      "<4EC0BC69>": 1078,
      "<7D1DE80F>": 1337,
      "<B138A4D8>": 1597,
      "<CF46B266>": 1860,
      "<78873410>": 2150,
      "<532A2A64>": 2416,
      "<E64DCC48>": 2677,
      "<F6B044EE>": 2934,
      "<52603A9C>": 0
    },
    {
      "$id": 15,
      "<DBEA0DF4>": "<4D10C09E>",
      "<A815E3A7>": 40,
      "<03053E2C>": 301,
      "<E04C8806>": 558,
      "<5DDB3CD8>": 821,
      "<4EC0BC69>": 1079,
      "<7D1DE80F>": 1338,
      "<B138A4D8>": 1598,
      "<CF46B266>": 1861,
      "<78873410>": 2151,
      "<532A2A64>": 2417,
      "<E64DCC48>": 2678,
      "<F6B044EE>": 2935,
      "<52603A9C>": 0
    },
    {
      "$id": 16,
      "<DBEA0DF4>": "<9C773A0B>",
      "<A815E3A7>": 41,
      "<03053E2C>": 302,
      "<E04C8806>": 559,
      "<5DDB3CD8>": 822,
      "<4EC0BC69>": 1080,
      "<7D1DE80F>": 1339,
      "<B138A4D8>": 1599,
      "<CF46B266>": 1862,
      "<78873410>": 2152,
      "<532A2A64>": 2418,
      "<E64DCC48>": 2679,
      "<F6B044EE>": 2936,
      "<52603A9C>": 0
    },
    {
      "$id": 17,
      "<DBEA0DF4>": "<1BF8B088>",
      "<A815E3A7>": 42,
      "<03053E2C>": 303,
      "<E04C8806>": 560,
      "<5DDB3CD8>": 823,
      "<4EC0BC69>": 1081,
      "<7D1DE80F>": 1340,
      "<B138A4D8>": 1600,
      "<CF46B266>": 1863,
      "<78873410>": 2153,
      "<532A2A64>": 2419,
      "<E64DCC48>": 2680,
      "<F6B044EE>": 2937,
      "<52603A9C>": 0
    },
    {
      "$id": 18,
      "<DBEA0DF4>": "<8ACAD9E4>",
      "<A815E3A7>": 43,
      "<03053E2C>": 304,
      "<E04C8806>": 561,
      "<5DDB3CD8>": 824,
      "<4EC0BC69>": 1082,
      "<7D1DE80F>": 1341,
      "<B138A4D8>": 1601,
      "<CF46B266>": 1864,
      "<78873410>": 2154,
      "<532A2A64>": 2420,
      "<E64DCC48>": 2681,
      "<F6B044EE>": 2938,
      "<52603A9C>": 0
    },
    {
      "$id": 19,
      "<DBEA0DF4>": "<D0A43B21>",
      "<A815E3A7>": 44,
      "<03053E2C>": 305,
      "<E04C8806>": 562,
      "<5DDB3CD8>": 825,
      "<4EC0BC69>": 1083,
      "<7D1DE80F>": 1342,
      "<B138A4D8>": 1602,
      "<CF46B266>": 1865,
      "<78873410>": 2155,
      "<532A2A64>": 2421,
      "<E64DCC48>": 2682,
      "<F6B044EE>": 2939,
      "<52603A9C>": 0
    },
    {
      "$id": 20,
      "<DBEA0DF4>": "<CB5E7BC8>",
      "<A815E3A7>": 45,
      "<03053E2C>": 306,
      "<E04C8806>": 563,
      "<5DDB3CD8>": 826,
      "<4EC0BC69>": 1084,
      "<7D1DE80F>": 1343,
      "<B138A4D8>": 1603,
      "<CF46B266>": 1866,
      "<78873410>": 2156,
      "<532A2A64>": 2422,
      "<E64DCC48>": 2683,
      "<F6B044EE>": 2940,
      "<52603A9C>": 0
    },
    {
      "$id": 21,
      "<DBEA0DF4>": "<71C76515>",
      "<A815E3A7>": 46,
      "<03053E2C>": 307,
      "<E04C8806>": 564,
      "<5DDB3CD8>": 827,
      "<4EC0BC69>": 1085,
      "<7D1DE80F>": 1344,
      "<B138A4D8>": 1604,
      "<CF46B266>": 1867,
      "<78873410>": 2157,
      "<532A2A64>": 2423,
      "<E64DCC48>": 2684,
      "<F6B044EE>": 2941,
      "<52603A9C>": 0
    },
    {
      "$id": 22,
      "<DBEA0DF4>": "<6AC6619D>",
      "<A815E3A7>": 47,
      "<03053E2C>": 308,
      "<E04C8806>": 565,
      "<5DDB3CD8>": 828,
      "<4EC0BC69>": 1086,
      "<7D1DE80F>": 1345,
      "<B138A4D8>": 1605,
      "<CF46B266>": 1868,
      "<78873410>": 2158,
      "<532A2A64>": 2424,
      "<E64DCC48>": 2685,
      "<F6B044EE>": 2942,
      "<52603A9C>": 0
    },
    {
      "$id": 23,
      "<DBEA0DF4>": "<E7B15DDF>",
      "<A815E3A7>": 48,
      "<03053E2C>": 309,
      "<E04C8806>": 566,
      "<5DDB3CD8>": 829,
      "<4EC0BC69>": 1087,
      "<7D1DE80F>": 1346,
      "<B138A4D8>": 1606,
      "<CF46B266>": 1869,
      "<78873410>": 2159,
      "<532A2A64>": 2425,
      "<E64DCC48>": 2686,
      "<F6B044EE>": 2943,
      "<52603A9C>": 0
    },
    {
      "$id": 24,
      "<DBEA0DF4>": "<163835F4>",
      "<A815E3A7>": 49,
      "<03053E2C>": 310,
      "<E04C8806>": 567,
      "<5DDB3CD8>": 830,
      "<4EC0BC69>": 1088,
      "<7D1DE80F>": 1347,
      "<B138A4D8>": 1607,
      "<CF46B266>": 1870,
      "<78873410>": 2160,
      "<532A2A64>": 2426,
      "<E64DCC48>": 2687,
      "<F6B044EE>": 2944,
      "<52603A9C>": 0
    },
    {
      "$id": 25,
      "<DBEA0DF4>": "<7192962B>",
      "<A815E3A7>": 50,
      "<03053E2C>": 311,
      "<E04C8806>": 568,
      "<5DDB3CD8>": 831,
      "<4EC0BC69>": 1089,
      "<7D1DE80F>": 1348,
      "<B138A4D8>": 1608,
      "<CF46B266>": 1871,
      "<78873410>": 2161,
      "<532A2A64>": 2427,
      "<E64DCC48>": 2688,
      "<F6B044EE>": 2945,
      "<52603A9C>": 0
    },
    {
      "$id": 26,
      "<DBEA0DF4>": "<3BCBF49B>",
      "<A815E3A7>": 51,
      "<03053E2C>": 312,
      "<E04C8806>": 569,
      "<5DDB3CD8>": 832,
      "<4EC0BC69>": 1090,
      "<7D1DE80F>": 1349,
      "<B138A4D8>": 1609,
      "<CF46B266>": 1872,
      "<78873410>": 2162,
      "<532A2A64>": 2428,
      "<E64DCC48>": 2689,
      "<F6B044EE>": 2946,
      "<52603A9C>": 0
    },
    {
      "$id": 27,
      "<DBEA0DF4>": "<1EE02E82>",
      "<A815E3A7>": 52,
      "<03053E2C>": 313,
      "<E04C8806>": 570,
      "<5DDB3CD8>": 833,
      "<4EC0BC69>": 1091,
      "<7D1DE80F>": 1350,
      "<B138A4D8>": 1610,
      "<CF46B266>": 1873,
      "<78873410>": 2163,
      "<532A2A64>": 2429,
      "<E64DCC48>": 2690,
      "<F6B044EE>": 2947,
      "<52603A9C>": 0
    },
    {
      "$id": 28,
      "<DBEA0DF4>": "<9264D624>",
      "<A815E3A7>": 53,
      "<03053E2C>": 314,
      "<E04C8806>": 571,
      "<5DDB3CD8>": 834,
      "<4EC0BC69>": 1092,
      "<7D1DE80F>": 1351,
      "<B138A4D8>": 1611,
      "<CF46B266>": 1874,
      "<78873410>": 2164,
      "<532A2A64>": 2430,
      "<E64DCC48>": 2691,
      "<F6B044EE>": 2948,
      "<52603A9C>": 0
    },
    {
      "$id": 29,
      "<DBEA0DF4>": "<DDBA6515>",
      "<A815E3A7>": 54,
      "<03053E2C>": 315,
      "<E04C8806>": 572,
      "<5DDB3CD8>": 835,
      "<4EC0BC69>": 1093,
      "<7D1DE80F>": 1352,
      "<B138A4D8>": 1612,
      "<CF46B266>": 1875,
      "<78873410>": 2165,
      "<532A2A64>": 2431,
      "<E64DCC48>": 2692,
      "<F6B044EE>": 2949,
      "<52603A9C>": 0
    },
    {
      "$id": 30,
      "<DBEA0DF4>": "<5F258289>",
      "<A815E3A7>": 55,
      "<03053E2C>": 316,
      "<E04C8806>": 573,
      "<5DDB3CD8>": 836,
      "<4EC0BC69>": 1094,
      "<7D1DE80F>": 1353,
      "<B138A4D8>": 1613,
      "<CF46B266>": 1876,
      "<78873410>": 2166,
      "<532A2A64>": 2432,
      "<E64DCC48>": 2693,
      "<F6B044EE>": 2950,
      "<52603A9C>": 0
    },
    {
      "$id": 31,
      "<DBEA0DF4>": "<4FE8604D>",
      "<A815E3A7>": 56,
      "<03053E2C>": 317,
      "<E04C8806>": 574,
      "<5DDB3CD8>": 837,
      "<4EC0BC69>": 1095,
      "<7D1DE80F>": 1354,
      "<B138A4D8>": 1614,
      "<CF46B266>": 1877,
      "<78873410>": 2167,
      "<532A2A64>": 2433,
      "<E64DCC48>": 2694,
      "<F6B044EE>": 2951,
      "<52603A9C>": 0
    },
    {
      "$id": 32,
      "<DBEA0DF4>": "<BCA83839>",
      "<A815E3A7>": 57,
      "<03053E2C>": 318,
      "<E04C8806>": 575,
      "<5DDB3CD8>": 838,
      "<4EC0BC69>": 1096,
      "<7D1DE80F>": 1355,
      "<B138A4D8>": 1615,
      "<CF46B266>": 1878,
      "<78873410>": 2168,
      "<532A2A64>": 2434,
      "<E64DCC48>": 2695,
      "<F6B044EE>": 2952,
      "<52603A9C>": 0
    },
    {
      "$id": 33,
      "<DBEA0DF4>": "<330AAE41>",
      "<A815E3A7>": 58,
      "<03053E2C>": 319,
      "<E04C8806>": 576,
      "<5DDB3CD8>": 839,
      "<4EC0BC69>": 1097,
      "<7D1DE80F>": 1356,
      "<B138A4D8>": 1616,
      "<CF46B266>": 1879,
      "<78873410>": 2169,
      "<532A2A64>": 2435,
      "<E64DCC48>": 2696,
      "<F6B044EE>": 2953,
      "<52603A9C>": 0
    },
    {
      "$id": 34,
      "<DBEA0DF4>": "<733F6C5B>",
      "<A815E3A7>": 59,
      "<03053E2C>": 320,
      "<E04C8806>": 577,
      "<5DDB3CD8>": 840,
      "<4EC0BC69>": 1098,
      "<7D1DE80F>": 1357,
      "<B138A4D8>": 1617,
      "<CF46B266>": 1880,
      "<78873410>": 2170,
      "<532A2A64>": 2436,
      "<E64DCC48>": 2697,
      "<F6B044EE>": 2954,
      "<52603A9C>": 0
    },
    {
      "$id": 35,
      "<DBEA0DF4>": "<CE8B0AC1>",
      "<A815E3A7>": 60,
      "<03053E2C>": 321,
      "<E04C8806>": 578,
      "<5DDB3CD8>": 841,
      "<4EC0BC69>": 1099,
      "<7D1DE80F>": 1358,
      "<B138A4D8>": 1618,
      "<CF46B266>": 1881,
      "<78873410>": 2171,
      "<532A2A64>": 2437,
      "<E64DCC48>": 2698,
      "<F6B044EE>": 2955,
      "<52603A9C>": 0
    },
    {
      "$id": 36,
      "<DBEA0DF4>": "<DD783EDA>",
      "<A815E3A7>": 61,
      "<03053E2C>": 322,
      "<E04C8806>": 579,
      "<5DDB3CD8>": 842,
      "<4EC0BC69>": 1100,
      "<7D1DE80F>": 1359,
      "<B138A4D8>": 1619,
      "<CF46B266>": 1882,
      "<78873410>": 2172,
      "<532A2A64>": 2438,
      "<E64DCC48>": 2699,
      "<F6B044EE>": 2956,
      "<52603A9C>": 0
    },
    {
      "$id": 37,
      "<DBEA0DF4>": "<4B29C0C7>",
      "<A815E3A7>": 62,
      "<03053E2C>": 323,
      "<E04C8806>": 580,
      "<5DDB3CD8>": 843,
      "<4EC0BC69>": 1101,
      "<7D1DE80F>": 1360,
      "<B138A4D8>": 1620,
      "<CF46B266>": 1883,
      "<78873410>": 2173,
      "<532A2A64>": 2439,
      "<E64DCC48>": 2700,
      "<F6B044EE>": 2957,
      "<52603A9C>": 0
    },
    {
      "$id": 38,
      "<DBEA0DF4>": "<A24E7EAA>",
      "<A815E3A7>": 63,
      "<03053E2C>": 324,
      "<E04C8806>": 581,
      "<5DDB3CD8>": 844,
      "<4EC0BC69>": 1102,
      "<7D1DE80F>": 1361,
      "<B138A4D8>": 1621,
      "<CF46B266>": 1884,
      "<78873410>": 2174,
      "<532A2A64>": 2440,
      "<E64DCC48>": 2701,
      "<F6B044EE>": 2958,
      "<52603A9C>": 0
    },
    {
      "$id": 39,
      "<DBEA0DF4>": "<312BFF13>",
      "<A815E3A7>": 64,
      "<03053E2C>": 325,
      "<E04C8806>": 582,
      "<5DDB3CD8>": 845,
      "<4EC0BC69>": 1103,
      "<7D1DE80F>": 1362,
      "<B138A4D8>": 1622,
      "<CF46B266>": 1885,
      "<78873410>": 2175,
      "<532A2A64>": 2441,
      "<E64DCC48>": 2702,
      "<F6B044EE>": 2959,
      "<52603A9C>": 0
    },
    {
      "$id": 40,
      "<DBEA0DF4>": "<9FD383F4>",
      "<A815E3A7>": 65,
      "<03053E2C>": 326,
      "<E04C8806>": 583,
      "<5DDB3CD8>": 846,
      "<4EC0BC69>": 1104,
      "<7D1DE80F>": 1363,
      "<B138A4D8>": 1623,
      "<CF46B266>": 1886,
      "<78873410>": 2176,
      "<532A2A64>": 2442,
      "<E64DCC48>": 2703,
      "<F6B044EE>": 2960,
      "<52603A9C>": 0
    },
    {
      "$id": 41,
      "<DBEA0DF4>": "<0EEECBC6>",
      "<A815E3A7>": 66,
      "<03053E2C>": 327,
      "<E04C8806>": 584,
      "<5DDB3CD8>": 847,
      "<4EC0BC69>": 1105,
      "<7D1DE80F>": 1364,
      "<B138A4D8>": 1624,
      "<CF46B266>": 1887,
      "<78873410>": 2177,
      "<532A2A64>": 2443,
      "<E64DCC48>": 2704,
      "<F6B044EE>": 2961,
      "<52603A9C>": 0
    },
    {
      "$id": 42,
      "<DBEA0DF4>": "<98136063>",
      "<A815E3A7>": 67,
      "<03053E2C>": 328,
      "<E04C8806>": 585,
      "<5DDB3CD8>": 848,
      "<4EC0BC69>": 1106,
      "<7D1DE80F>": 1365,
      "<B138A4D8>": 1625,
      "<CF46B266>": 1888,
      "<78873410>": 2178,
      "<532A2A64>": 2444,
      "<E64DCC48>": 2705,
      "<F6B044EE>": 2962,
      "<52603A9C>": 0
    },
    {
      "$id": 43,
      "<DBEA0DF4>": "<4AAC83B8>",
      "<A815E3A7>": 68,
      "<03053E2C>": 329,
      "<E04C8806>": 586,
      "<5DDB3CD8>": 852,
      "<4EC0BC69>": 1107,
      "<7D1DE80F>": 1366,
      "<B138A4D8>": 1626,
      "<CF46B266>": 1889,
      "<78873410>": 2179,
      "<532A2A64>": 2445,
      "<E64DCC48>": 2706,
      "<F6B044EE>": 2966,
      "<52603A9C>": 0
    },
    {
      "$id": 44,
      "<DBEA0DF4>": "<5C8FB3D1>",
      "<A815E3A7>": 69,
      "<03053E2C>": 330,
      "<E04C8806>": 587,
      "<5DDB3CD8>": 853,
      "<4EC0BC69>": 1108,
      "<7D1DE80F>": 1367,
      "<B138A4D8>": 1627,
      "<CF46B266>": 1890,
      "<78873410>": 2180,
      "<532A2A64>": 2446,
      "<E64DCC48>": 2707,
      "<F6B044EE>": 2967,
      "<52603A9C>": 0
    },
    {
      "$id": 45,
      "<DBEA0DF4>": "<612DB3E2>",
      "<A815E3A7>": 70,
      "<03053E2C>": 331,
      "<E04C8806>": 588,
      "<5DDB3CD8>": 854,
      "<4EC0BC69>": 1109,
      "<7D1DE80F>": 1368,
      "<B138A4D8>": 1628,
      "<CF46B266>": 1891,
      "<78873410>": 2181,
      "<532A2A64>": 2447,
      "<E64DCC48>": 2708,
      "<F6B044EE>": 2968,
      "<52603A9C>": 0
    },
    {
      "$id": 46,
      "<DBEA0DF4>": "<02F86C31>",
      "<A815E3A7>": 71,
      "<03053E2C>": 332,
      "<E04C8806>": 589,
      "<5DDB3CD8>": 855,
      "<4EC0BC69>": 1110,
      "<7D1DE80F>": 1369,
      "<B138A4D8>": 1629,
      "<CF46B266>": 1892,
      "<78873410>": 2182,
      "<532A2A64>": 2448,
      "<E64DCC48>": 2709,
      "<F6B044EE>": 2969,
      "<52603A9C>": 0
    },
    {
      "$id": 47,
      "<DBEA0DF4>": "<22C8C828>",
      "<A815E3A7>": 72,
      "<03053E2C>": 333,
      "<E04C8806>": 590,
      "<5DDB3CD8>": 856,
      "<4EC0BC69>": 1111,
      "<7D1DE80F>": 1370,
      "<B138A4D8>": 1630,
      "<CF46B266>": 1893,
      "<78873410>": 2183,
      "<532A2A64>": 2449,
      "<E64DCC48>": 2710,
      "<F6B044EE>": 2970,
      "<52603A9C>": 0
    },
    {
      "$id": 48,
      "<DBEA0DF4>": "<0116D9F2>",
      "<A815E3A7>": 73,
      "<03053E2C>": 334,
      "<E04C8806>": 591,
      "<5DDB3CD8>": 857,
      "<4EC0BC69>": 1112,
      "<7D1DE80F>": 1371,
      "<B138A4D8>": 1631,
      "<CF46B266>": 1894,
      "<78873410>": 2184,
      "<532A2A64>": 2450,
      "<E64DCC48>": 2711,
      "<F6B044EE>": 2971,
      "<52603A9C>": 0
    },
    {
      "$id": 49,
      "<DBEA0DF4>": "<3AA8861C>",
      "<A815E3A7>": 74,
      "<03053E2C>": 335,
      "<E04C8806>": 592,
      "<5DDB3CD8>": 858,
      "<4EC0BC69>": 1113,
      "<7D1DE80F>": 1372,
      "<B138A4D8>": 1632,
      "<CF46B266>": 1895,
      "<78873410>": 2185,
      "<532A2A64>": 2451,
      "<E64DCC48>": 2712,
      "<F6B044EE>": 2972,
      "<52603A9C>": 0
    },
    {
      "$id": 50,
      "<DBEA0DF4>": "<3E692CBA>",
      "<A815E3A7>": 75,
      "<03053E2C>": 336,
      "<E04C8806>": 593,
      "<5DDB3CD8>": 859,
      "<4EC0BC69>": 1114,
      "<7D1DE80F>": 1373,
      "<B138A4D8>": 1633,
      "<CF46B266>": 1896,
      "<78873410>": 2186,
      "<532A2A64>": 2452,
      "<E64DCC48>": 2713,
      "<F6B044EE>": 2973,
      "<52603A9C>": 0
    },
    {
      "$id": 51,
      "<DBEA0DF4>": "<835844EA>",
      "<A815E3A7>": 76,
      "<03053E2C>": 337,
      "<E04C8806>": 594,
      "<5DDB3CD8>": 860,
      "<4EC0BC69>": 1115,
      "<7D1DE80F>": 1374,
      "<B138A4D8>": 1634,
      "<CF46B266>": 1897,
      "<78873410>": 2187,
      "<532A2A64>": 2453,
      "<E64DCC48>": 2714,
      "<F6B044EE>": 2974,
      "<52603A9C>": 0
    },
    {
      "$id": 52,
      "<DBEA0DF4>": "<7C16E12E>",
      "<A815E3A7>": 77,
      "<03053E2C>": 338,
      "<E04C8806>": 595,
      "<5DDB3CD8>": 861,
      "<4EC0BC69>": 1116,
      "<7D1DE80F>": 1375,
      "<B138A4D8>": 1635,
      "<CF46B266>": 1898,
      "<78873410>": 2188,
      "<532A2A64>": 2454,
      "<E64DCC48>": 2715,
      "<F6B044EE>": 2975,
      "<52603A9C>": 0
    },
    {
      "$id": 53,
      "<DBEA0DF4>": "<A4D2F753>",
      "<A815E3A7>": 78,
      "<03053E2C>": 339,
      "<E04C8806>": 596,
      "<5DDB3CD8>": 862,
      "<4EC0BC69>": 1117,
      "<7D1DE80F>": 1376,
      "<B138A4D8>": 1636,
      "<CF46B266>": 1899,
      "<78873410>": 2189,
      "<532A2A64>": 2455,
      "<E64DCC48>": 2716,
      "<F6B044EE>": 2976,
      "<52603A9C>": 0
    },
    {
      "$id": 54,
      "<DBEA0DF4>": "<549634AC>",
      "<A815E3A7>": 79,
      "<03053E2C>": 340,
      "<E04C8806>": 597,
      "<5DDB3CD8>": 863,
      "<4EC0BC69>": 1118,
      "<7D1DE80F>": 1377,
      "<B138A4D8>": 1637,
      "<CF46B266>": 1900,
      "<78873410>": 2190,
      "<532A2A64>": 2456,
      "<E64DCC48>": 2717,
      "<F6B044EE>": 2977,
      "<52603A9C>": 0
    },
    {
      "$id": 55,
      "<DBEA0DF4>": "<47CD611E>",
      "<A815E3A7>": 80,
      "<03053E2C>": 341,
      "<E04C8806>": 598,
      "<5DDB3CD8>": 864,
      "<4EC0BC69>": 1119,
      "<7D1DE80F>": 1378,
      "<B138A4D8>": 1638,
      "<CF46B266>": 1901,
      "<78873410>": 2191,
      "<532A2A64>": 2457,
      "<E64DCC48>": 2718,
      "<F6B044EE>": 2978,
      "<52603A9C>": 0
    },
    {
      "$id": 56,
      "<DBEA0DF4>": "<EAD0C692>",
      "<A815E3A7>": 81,
      "<03053E2C>": 342,
      "<E04C8806>": 599,
      "<5DDB3CD8>": 865,
      "<4EC0BC69>": 1120,
      "<7D1DE80F>": 1379,
      "<B138A4D8>": 1639,
      "<CF46B266>": 1902,
      "<78873410>": 2192,
      "<532A2A64>": 2458,
      "<E64DCC48>": 2719,
      "<F6B044EE>": 2979,
      "<52603A9C>": 0
    },
    {
      "$id": 57,
      "<DBEA0DF4>": "<D1AD95F0>",
      "<A815E3A7>": 82,
      "<03053E2C>": 343,
      "<E04C8806>": 600,
      "<5DDB3CD8>": 866,
      "<4EC0BC69>": 1121,
      "<7D1DE80F>": 1380,
      "<B138A4D8>": 1640,
      "<CF46B266>": 1903,
      "<78873410>": 2193,
      "<532A2A64>": 2459,
      "<E64DCC48>": 2720,
      "<F6B044EE>": 2980,
      "<52603A9C>": 0
    },
    {
      "$id": 58,
      "<DBEA0DF4>": "<E8482B30>",
      "<A815E3A7>": 83,
      "<03053E2C>": 344,
      "<E04C8806>": 601,
      "<5DDB3CD8>": 867,
      "<4EC0BC69>": 1122,
      "<7D1DE80F>": 1381,
      "<B138A4D8>": 1641,
      "<CF46B266>": 1904,
      "<78873410>": 2194,
      "<532A2A64>": 2460,
      "<E64DCC48>": 2721,
      "<F6B044EE>": 2981,
      "<52603A9C>": 0
    },
    {
      "$id": 59,
      "<DBEA0DF4>": "<8278753B>",
      "<A815E3A7>": 84,
      "<03053E2C>": 345,
      "<E04C8806>": 602,
      "<5DDB3CD8>": 868,
      "<4EC0BC69>": 1123,
      "<7D1DE80F>": 1382,
      "<B138A4D8>": 1642,
      "<CF46B266>": 1905,
      "<78873410>": 2195,
      "<532A2A64>": 2461,
      "<E64DCC48>": 2722,
      "<F6B044EE>": 2982,
      "<52603A9C>": 0
    },
    {
      "$id": 60,
      "<DBEA0DF4>": "<2BACB52F>",
      "<A815E3A7>": 85,
      "<03053E2C>": 346,
      "<E04C8806>": 603,
      "<5DDB3CD8>": 869,
      "<4EC0BC69>": 1124,
      "<7D1DE80F>": 1383,
      "<B138A4D8>": 1643,
      "<CF46B266>": 1906,
      "<78873410>": 2196,
      "<532A2A64>": 2462,
      "<E64DCC48>": 2723,
      "<F6B044EE>": 2983,
      "<52603A9C>": 0
    },
    {
      "$id": 61,
      "<DBEA0DF4>": "<88C43515>",
      "<A815E3A7>": 86,
      "<03053E2C>": 347,
      "<E04C8806>": 604,
      "<5DDB3CD8>": 873,
      "<4EC0BC69>": 1125,
      "<7D1DE80F>": 1384,
      "<B138A4D8>": 1644,
      "<CF46B266>": 1907,
      "<78873410>": 2197,
      "<532A2A64>": 2463,
      "<E64DCC48>": 2724,
      "<F6B044EE>": 2987,
      "<52603A9C>": 0
    },
    {
      "$id": 62,
      "<DBEA0DF4>": "<C453BFCE>",
      "<A815E3A7>": 87,
      "<03053E2C>": 348,
      "<E04C8806>": 605,
      "<5DDB3CD8>": 874,
      "<4EC0BC69>": 1126,
      "<7D1DE80F>": 1385,
      "<B138A4D8>": 1645,
      "<CF46B266>": 1908,
      "<78873410>": 2198,
      "<532A2A64>": 2464,
      "<E64DCC48>": 2725,
      "<F6B044EE>": 2988,
      "<52603A9C>": 0
    },
    {
      "$id": 63,
      "<DBEA0DF4>": "<57E32757>",
      "<A815E3A7>": 88,
      "<03053E2C>": 349,
      "<E04C8806>": 606,
      "<5DDB3CD8>": 875,
      "<4EC0BC69>": 1127,
      "<7D1DE80F>": 1386,
      "<B138A4D8>": 1646,
      "<CF46B266>": 1909,
      "<78873410>": 2199,
      "<532A2A64>": 2465,
      "<E64DCC48>": 2726,
      "<F6B044EE>": 2989,
      "<52603A9C>": 0
    },
    {
      "$id": 64,
      "<DBEA0DF4>": "<460646AF>",
      "<A815E3A7>": 89,
      "<03053E2C>": 353,
      "<E04C8806>": 607,
      "<5DDB3CD8>": 876,
      "<4EC0BC69>": 1131,
      "<7D1DE80F>": 1390,
      "<B138A4D8>": 1647,
      "<CF46B266>": 1913,
      "<78873410>": 2200,
      "<532A2A64>": 2469,
      "<E64DCC48>": 2730,
      "<F6B044EE>": 2990,
      "<52603A9C>": 0
    },
    {
      "$id": 65,
      "<DBEA0DF4>": "<428EDB10>",
      "<A815E3A7>": 90,
      "<03053E2C>": 354,
      "<E04C8806>": 608,
      "<5DDB3CD8>": 877,
      "<4EC0BC69>": 1132,
      "<7D1DE80F>": 1391,
      "<B138A4D8>": 1648,
      "<CF46B266>": 1914,
      "<78873410>": 2201,
      "<532A2A64>": 2470,
      "<E64DCC48>": 2731,
      "<F6B044EE>": 2991,
      "<52603A9C>": 0
    },
    {
      "$id": 66,
      "<DBEA0DF4>": "<4BA5CADD>",
      "<A815E3A7>": 91,
      "<03053E2C>": 355,
      "<E04C8806>": 609,
      "<5DDB3CD8>": 878,
      "<4EC0BC69>": 1133,
      "<7D1DE80F>": 1392,
      "<B138A4D8>": 1649,
      "<CF46B266>": 1915,
      "<78873410>": 2202,
      "<532A2A64>": 2471,
      "<E64DCC48>": 2732,
      "<F6B044EE>": 2992,
      "<52603A9C>": 0
    },
    {
      "$id": 67,
      "<DBEA0DF4>": "<8591E0AA>",
      "<A815E3A7>": 92,
      "<03053E2C>": 356,
      "<E04C8806>": 610,
      "<5DDB3CD8>": 879,
      "<4EC0BC69>": 1134,
      "<7D1DE80F>": 1393,
      "<B138A4D8>": 1650,
      "<CF46B266>": 1916,
      "<78873410>": 2203,
      "<532A2A64>": 2472,
      "<E64DCC48>": 2733,
      "<F6B044EE>": 2993,
      "<52603A9C>": 0
    },
    {
      "$id": 68,
      "<DBEA0DF4>": "<71125325>",
      "<A815E3A7>": 93,
      "<03053E2C>": 357,
      "<E04C8806>": 611,
      "<5DDB3CD8>": 880,
      "<4EC0BC69>": 1135,
      "<7D1DE80F>": 1394,
      "<B138A4D8>": 1651,
      "<CF46B266>": 1917,
      "<78873410>": 2204,
      "<532A2A64>": 2473,
      "<E64DCC48>": 2734,
      "<F6B044EE>": 2994,
      "<52603A9C>": 0
    },
    {
      "$id": 69,
      "<DBEA0DF4>": "<D711715E>",
      "<A815E3A7>": 94,
      "<03053E2C>": 358,
      "<E04C8806>": 612,
      "<5DDB3CD8>": 881,
      "<4EC0BC69>": 1136,
      "<7D1DE80F>": 1395,
      "<B138A4D8>": 1652,
      "<CF46B266>": 1918,
      "<78873410>": 2205,
      "<532A2A64>": 2474,
      "<E64DCC48>": 2735,
      "<F6B044EE>": 2995,
      "<52603A9C>": 0
    },
    {
      "$id": 70,
      "<DBEA0DF4>": "<7B5F3E79>",
      "<A815E3A7>": 95,
      "<03053E2C>": 359,
      "<E04C8806>": 613,
      "<5DDB3CD8>": 882,
      "<4EC0BC69>": 1137,
      "<7D1DE80F>": 1396,
      "<B138A4D8>": 1653,
      "<CF46B266>": 1919,
      "<78873410>": 2206,
      "<532A2A64>": 2475,
      "<E64DCC48>": 2736,
      "<F6B044EE>": 2996,
      "<52603A9C>": 0
    },
    {
      "$id": 71,
      "<DBEA0DF4>": "<97C53068>",
      "<A815E3A7>": 96,
      "<03053E2C>": 360,
      "<E04C8806>": 614,
      "<5DDB3CD8>": 883,
      "<4EC0BC69>": 1138,
      "<7D1DE80F>": 1397,
      "<B138A4D8>": 1654,
      "<CF46B266>": 1920,
      "<78873410>": 2207,
      "<532A2A64>": 2476,
      "<E64DCC48>": 2737,
      "<F6B044EE>": 2997,
      "<52603A9C>": 0
    },
    {
      "$id": 72,
      "<DBEA0DF4>": "<917649C9>",
      "<A815E3A7>": 97,
      "<03053E2C>": 361,
      "<E04C8806>": 615,
      "<5DDB3CD8>": 884,
      "<4EC0BC69>": 1139,
      "<7D1DE80F>": 1398,
      "<B138A4D8>": 1655,
      "<CF46B266>": 1921,
      "<78873410>": 2208,
      "<532A2A64>": 2477,
      "<E64DCC48>": 2738,
      "<F6B044EE>": 2998,
      "<52603A9C>": 0
    },
    {
      "$id": 73,
      "<DBEA0DF4>": "<481C814A>",
      "<A815E3A7>": 98,
      "<03053E2C>": 362,
      "<E04C8806>": 616,
      "<5DDB3CD8>": 885,
      "<4EC0BC69>": 1140,
      "<7D1DE80F>": 1399,
      "<B138A4D8>": 1656,
      "<CF46B266>": 1922,
      "<78873410>": 2209,
      "<532A2A64>": 2478,
      "<E64DCC48>": 2739,
      "<F6B044EE>": 2999,
      "<52603A9C>": 0
    },
    {
      "$id": 74,
      "<DBEA0DF4>": "<E4BEBBC3>",
      "<A815E3A7>": 99,
      "<03053E2C>": 363,
      "<E04C8806>": 617,
      "<5DDB3CD8>": 886,
      "<4EC0BC69>": 1141,
      "<7D1DE80F>": 1400,
      "<B138A4D8>": 1657,
      "<CF46B266>": 1923,
      "<78873410>": 2210,
      "<532A2A64>": 2479,
      "<E64DCC48>": 2740,
      "<F6B044EE>": 3000,
      "<52603A9C>": 0
    },
    {
      "$id": 75,
      "<DBEA0DF4>": "<24784CDE>",
      "<A815E3A7>": 100,
      "<03053E2C>": 364,
      "<E04C8806>": 618,
      "<5DDB3CD8>": 887,
      "<4EC0BC69>": 1142,
      "<7D1DE80F>": 1401,
      "<B138A4D8>": 1658,
      "<CF46B266>": 1924,
      "<78873410>": 2211,
      "<532A2A64>": 2480,
      "<E64DCC48>": 2741,
      "<F6B044EE>": 3001,
      "<52603A9C>": 0
    },
    {
      "$id": 76,
      "<DBEA0DF4>": "<028B71A6>",
      "<A815E3A7>": 101,
      "<03053E2C>": 365,
      "<E04C8806>": 619,
      "<5DDB3CD8>": 888,
      "<4EC0BC69>": 1143,
      "<7D1DE80F>": 1402,
      "<B138A4D8>": 1659,
      "<CF46B266>": 1925,
      "<78873410>": 2212,
      "<532A2A64>": 2481,
      "<E64DCC48>": 2742,
      "<F6B044EE>": 3002,
      "<52603A9C>": 0
    },
    {
      "$id": 77,
      "<DBEA0DF4>": "<588AD8F2>",
      "<A815E3A7>": 102,
      "<03053E2C>": 366,
      "<E04C8806>": 620,
      "<5DDB3CD8>": 889,
      "<4EC0BC69>": 1144,
      "<7D1DE80F>": 1403,
      "<B138A4D8>": 1660,
      "<CF46B266>": 1926,
      "<78873410>": 2213,
      "<532A2A64>": 2482,
      "<E64DCC48>": 2743,
      "<F6B044EE>": 3003,
      "<52603A9C>": 0
    },
    {
      "$id": 78,
      "<DBEA0DF4>": "<2360DB74>",
      "<A815E3A7>": 103,
      "<03053E2C>": 367,
      "<E04C8806>": 621,
      "<5DDB3CD8>": 890,
      "<4EC0BC69>": 1145,
      "<7D1DE80F>": 1404,
      "<B138A4D8>": 1661,
      "<CF46B266>": 1927,
      "<78873410>": 2214,
      "<532A2A64>": 2483,
      "<E64DCC48>": 2744,
      "<F6B044EE>": 3004,
      "<52603A9C>": 0
    },
    {
      "$id": 79,
      "<DBEA0DF4>": "<DBC839C3>",
      "<A815E3A7>": 104,
      "<03053E2C>": 368,
      "<E04C8806>": 622,
      "<5DDB3CD8>": 897,
      "<4EC0BC69>": 1146,
      "<7D1DE80F>": 1405,
      "<B138A4D8>": 1662,
      "<CF46B266>": 1928,
      "<78873410>": 2215,
      "<532A2A64>": 2484,
      "<E64DCC48>": 2745,
      "<F6B044EE>": 3008,
      "<52603A9C>": 0
    },
    {
      "$id": 80,
      "<DBEA0DF4>": "<268D8F80>",
      "<A815E3A7>": 105,
      "<03053E2C>": 369,
      "<E04C8806>": 623,
      "<5DDB3CD8>": 898,
      "<4EC0BC69>": 1147,
      "<7D1DE80F>": 1406,
      "<B138A4D8>": 1663,
      "<CF46B266>": 1929,
      "<78873410>": 2216,
      "<532A2A64>": 2485,
      "<E64DCC48>": 2746,
      "<F6B044EE>": 3009,
      "<52603A9C>": 0
    },
    {
      "$id": 81,
      "<DBEA0DF4>": "<2075BF48>",
      "<A815E3A7>": 106,
      "<03053E2C>": 370,
      "<E04C8806>": 624,
      "<5DDB3CD8>": 899,
      "<4EC0BC69>": 1148,
      "<7D1DE80F>": 1407,
      "<B138A4D8>": 1664,
      "<CF46B266>": 1930,
      "<78873410>": 2217,
      "<532A2A64>": 2486,
      "<E64DCC48>": 2747,
      "<F6B044EE>": 3010,
      "<52603A9C>": 0
    },
    {
      "$id": 82,
      "<DBEA0DF4>": "<51261C65>",
      "<A815E3A7>": 107,
      "<03053E2C>": 377,
      "<E04C8806>": 625,
      "<5DDB3CD8>": 900,
      "<4EC0BC69>": 1152,
      "<7D1DE80F>": 1411,
      "<B138A4D8>": 1665,
      "<CF46B266>": 1937,
      "<78873410>": 2218,
      "<532A2A64>": 2490,
      "<E64DCC48>": 2754,
      "<F6B044EE>": 3011,
      "<52603A9C>": 0
    },
    {
      "$id": 83,
      "<DBEA0DF4>": "<EDEFB109>",
      "<A815E3A7>": 108,
      "<03053E2C>": 378,
      "<E04C8806>": 626,
      "<5DDB3CD8>": 901,
      "<4EC0BC69>": 1153,
      "<7D1DE80F>": 1412,
      "<B138A4D8>": 1666,
      "<CF46B266>": 1938,
      "<78873410>": 2219,
      "<532A2A64>": 2491,
      "<E64DCC48>": 2755,
      "<F6B044EE>": 3012,
      "<52603A9C>": 0
    },
    {
      "$id": 84,
      "<DBEA0DF4>": "<083E1728>",
      "<A815E3A7>": 109,
      "<03053E2C>": 379,
      "<E04C8806>": 627,
      "<5DDB3CD8>": 902,
      "<4EC0BC69>": 1154,
      "<7D1DE80F>": 1413,
      "<B138A4D8>": 1667,
      "<CF46B266>": 1939,
      "<78873410>": 2220,
      "<532A2A64>": 2492,
      "<E64DCC48>": 2756,
      "<F6B044EE>": 3013,
      "<52603A9C>": 0
    },
    {
      "$id": 85,
      "<DBEA0DF4>": "<B0EE3DCF>",
      "<A815E3A7>": 113,
      "<03053E2C>": 380,
      "<E04C8806>": 631,
      "<5DDB3CD8>": 903,
      "<4EC0BC69>": 1155,
      "<7D1DE80F>": 1414,
      "<B138A4D8>": 1671,
      "<CF46B266>": 1940,
      "<78873410>": 2224,
      "<532A2A64>": 2493,
      "<E64DCC48>": 2757,
      "<F6B044EE>": 3014,
      "<52603A9C>": 0
    },
    {
      "$id": 86,
      "<DBEA0DF4>": "<AFF32D77>",
      "<A815E3A7>": 114,
      "<03053E2C>": 381,
      "<E04C8806>": 632,
      "<5DDB3CD8>": 904,
      "<4EC0BC69>": 1156,
      "<7D1DE80F>": 1415,
      "<B138A4D8>": 1672,
      "<CF46B266>": 1941,
      "<78873410>": 2225,
      "<532A2A64>": 2494,
      "<E64DCC48>": 2758,
      "<F6B044EE>": 3015,
      "<52603A9C>": 0
    },
    {
      "$id": 87,
      "<DBEA0DF4>": "<F05D553B>",
      "<A815E3A7>": 115,
      "<03053E2C>": 382,
      "<E04C8806>": 633,
      "<5DDB3CD8>": 905,
      "<4EC0BC69>": 1157,
      "<7D1DE80F>": 1416,
      "<B138A4D8>": 1673,
      "<CF46B266>": 1942,
      "<78873410>": 2226,
      "<532A2A64>": 2495,
      "<E64DCC48>": 2759,
      "<F6B044EE>": 3016,
      "<52603A9C>": 0
    },
    {
      "$id": 88,
      "<DBEA0DF4>": "<3DB1A180>",
      "<A815E3A7>": 116,
      "<03053E2C>": 383,
      "<E04C8806>": 634,
      "<5DDB3CD8>": 906,
      "<4EC0BC69>": 1158,
      "<7D1DE80F>": 1417,
      "<B138A4D8>": 1674,
      "<CF46B266>": 1943,
      "<78873410>": 2227,
      "<532A2A64>": 2496,
      "<E64DCC48>": 2760,
      "<F6B044EE>": 3017,
      "<52603A9C>": 0
    },
    {
      "$id": 89,
      "<DBEA0DF4>": "<93BE04BE>",
      "<A815E3A7>": 117,
      "<03053E2C>": 384,
      "<E04C8806>": 635,
      "<5DDB3CD8>": 907,
      "<4EC0BC69>": 1159,
      "<7D1DE80F>": 1418,
      "<B138A4D8>": 1675,
      "<CF46B266>": 1944,
      "<78873410>": 2228,
      "<532A2A64>": 2497,
      "<E64DCC48>": 2761,
      "<F6B044EE>": 3018,
      "<52603A9C>": 0
    },
    {
      "$id": 90,
      "<DBEA0DF4>": "<D236579F>",
      "<A815E3A7>": 118,
      "<03053E2C>": 385,
      "<E04C8806>": 636,
      "<5DDB3CD8>": 908,
      "<4EC0BC69>": 1160,
      "<7D1DE80F>": 1419,
      "<B138A4D8>": 1676,
      "<CF46B266>": 1945,
      "<78873410>": 2229,
      "<532A2A64>": 2498,
      "<E64DCC48>": 2762,
      "<F6B044EE>": 3019,
      "<52603A9C>": 0
    },
    {
      "$id": 91,
      "<DBEA0DF4>": "<5C66D4A7>",
      "<A815E3A7>": 119,
      "<03053E2C>": 386,
      "<E04C8806>": 637,
      "<5DDB3CD8>": 909,
      "<4EC0BC69>": 1161,
      "<7D1DE80F>": 1420,
      "<B138A4D8>": 1677,
      "<CF46B266>": 1946,
      "<78873410>": 2230,
      "<532A2A64>": 2499,
      "<E64DCC48>": 2763,
      "<F6B044EE>": 3020,
      "<52603A9C>": 0
    },
    {
      "$id": 92,
      "<DBEA0DF4>": "<B4637369>",
      "<A815E3A7>": 120,
      "<03053E2C>": 387,
      "<E04C8806>": 638,
      "<5DDB3CD8>": 910,
      "<4EC0BC69>": 1162,
      "<7D1DE80F>": 1421,
      "<B138A4D8>": 1678,
      "<CF46B266>": 1947,
      "<78873410>": 2231,
      "<532A2A64>": 2500,
      "<E64DCC48>": 2764,
      "<F6B044EE>": 3021,
      "<52603A9C>": 0
    },
    {
      "$id": 93,
      "<DBEA0DF4>": "<79531986>",
      "<A815E3A7>": 121,
      "<03053E2C>": 388,
      "<E04C8806>": 639,
      "<5DDB3CD8>": 911,
      "<4EC0BC69>": 1163,
      "<7D1DE80F>": 1422,
      "<B138A4D8>": 1679,
      "<CF46B266>": 1948,
      "<78873410>": 2232,
      "<532A2A64>": 2501,
      "<E64DCC48>": 2765,
      "<F6B044EE>": 3022,
      "<52603A9C>": 0
    },
    {
      "$id": 94,
      "<DBEA0DF4>": "<30111581>",
      "<A815E3A7>": 122,
      "<03053E2C>": 389,
      "<E04C8806>": 640,
      "<5DDB3CD8>": 918,
      "<4EC0BC69>": 1164,
      "<7D1DE80F>": 1423,
      "<B138A4D8>": 1680,
      "<CF46B266>": 1949,
      "<78873410>": 2233,
      "<532A2A64>": 2502,
      "<E64DCC48>": 2766,
      "<F6B044EE>": 3023,
      "<52603A9C>": 0
    },
    {
      "$id": 95,
      "<DBEA0DF4>": "<54807CD1>",
      "<A815E3A7>": 123,
      "<03053E2C>": 390,
      "<E04C8806>": 641,
      "<5DDB3CD8>": 919,
      "<4EC0BC69>": 1165,
      "<7D1DE80F>": 1424,
      "<B138A4D8>": 1681,
      "<CF46B266>": 1950,
      "<78873410>": 2234,
      "<532A2A64>": 2503,
      "<E64DCC48>": 2767,
      "<F6B044EE>": 3024,
      "<52603A9C>": 0
    },
    {
      "$id": 96,
      "<DBEA0DF4>": "<64A61896>",
      "<A815E3A7>": 124,
      "<03053E2C>": 391,
      "<E04C8806>": 642,
      "<5DDB3CD8>": 920,
      "<4EC0BC69>": 1166,
      "<7D1DE80F>": 1425,
      "<B138A4D8>": 1682,
      "<CF46B266>": 1951,
      "<78873410>": 2235,
      "<532A2A64>": 2504,
      "<E64DCC48>": 2768,
      "<F6B044EE>": 3025,
      "<52603A9C>": 0
    },
    {
      "$id": 97,
      "<DBEA0DF4>": "<60D079F5>",
      "<A815E3A7>": 125,
      "<03053E2C>": 398,
      "<E04C8806>": 643,
      "<5DDB3CD8>": 921,
      "<4EC0BC69>": 1167,
      "<7D1DE80F>": 1426,
      "<B138A4D8>": 1683,
      "<CF46B266>": 1958,
      "<78873410>": 2236,
      "<532A2A64>": 2505,
      "<E64DCC48>": 2775,
      "<F6B044EE>": 3032,
      "<52603A9C>": 0
    },
    {
      "$id": 98,
      "<DBEA0DF4>": "<9125E745>",
      "<A815E3A7>": 126,
      "<03053E2C>": 399,
      "<E04C8806>": 644,
      "<5DDB3CD8>": 922,
      "<4EC0BC69>": 1168,
      "<7D1DE80F>": 1427,
      "<B138A4D8>": 1684,
      "<CF46B266>": 1959,
      "<78873410>": 2237,
      "<532A2A64>": 2506,
      "<E64DCC48>": 2776,
      "<F6B044EE>": 3033,
      "<52603A9C>": 0
    },
    {
      "$id": 99,
      "<DBEA0DF4>": "<608B23EF>",
      "<A815E3A7>": 127,
      "<03053E2C>": 400,
      "<E04C8806>": 645,
      "<5DDB3CD8>": 923,
      "<4EC0BC69>": 1169,
      "<7D1DE80F>": 1428,
      "<B138A4D8>": 1685,
      "<CF46B266>": 1960,
      "<78873410>": 2238,
      "<532A2A64>": 2507,
      "<E64DCC48>": 2777,
      "<F6B044EE>": 3034,
      "<52603A9C>": 0
    },
    {
      "$id": 100,
      "<DBEA0DF4>": "<B52A180D>",
      "<A815E3A7>": 128,
      "<03053E2C>": 401,
      "<E04C8806>": 646,
      "<5DDB3CD8>": 924,
      "<4EC0BC69>": 1170,
      "<7D1DE80F>": 1432,
      "<B138A4D8>": 1686,
      "<CF46B266>": 1961,
      "<78873410>": 2239,
      "<532A2A64>": 2514,
      "<E64DCC48>": 2778,
      "<F6B044EE>": 3035,
      "<52603A9C>": 0
    },
    {
      "$id": 101,
      "<DBEA0DF4>": "<0792CBD6>",
      "<A815E3A7>": 129,
      "<03053E2C>": 402,
      "<E04C8806>": 647,
      "<5DDB3CD8>": 925,
      "<4EC0BC69>": 1171,
      "<7D1DE80F>": 1433,
      "<B138A4D8>": 1687,
      "<CF46B266>": 1962,
      "<78873410>": 2240,
      "<532A2A64>": 2515,
      "<E64DCC48>": 2779,
      "<F6B044EE>": 3036,
      "<52603A9C>": 0
    },
    {
      "$id": 102,
      "<DBEA0DF4>": "<1826958B>",
      "<A815E3A7>": 130,
      "<03053E2C>": 403,
      "<E04C8806>": 648,
      "<5DDB3CD8>": 926,
      "<4EC0BC69>": 1172,
      "<7D1DE80F>": 1434,
      "<B138A4D8>": 1688,
      "<CF46B266>": 1963,
      "<78873410>": 2241,
      "<532A2A64>": 2516,
      "<E64DCC48>": 2780,
      "<F6B044EE>": 3037,
      "<52603A9C>": 0
    },
    {
      "$id": 103,
      "<DBEA0DF4>": "<9AC50DDC>",
      "<A815E3A7>": 137,
      "<03053E2C>": 404,
      "<E04C8806>": 655,
      "<5DDB3CD8>": 927,
      "<4EC0BC69>": 1176,
      "<7D1DE80F>": 1435,
      "<B138A4D8>": 1695,
      "<CF46B266>": 1964,
      "<78873410>": 2245,
      "<532A2A64>": 2517,
      "<E64DCC48>": 2781,
      "<F6B044EE>": 3038,
      "<52603A9C>": 0
    },
    {
      "$id": 104,
      "<DBEA0DF4>": "<51132E1E>",
      "<A815E3A7>": 138,
      "<03053E2C>": 405,
      "<E04C8806>": 656,
      "<5DDB3CD8>": 928,
      "<4EC0BC69>": 1177,
      "<7D1DE80F>": 1436,
      "<B138A4D8>": 1696,
      "<CF46B266>": 1965,
      "<78873410>": 2246,
      "<532A2A64>": 2518,
      "<E64DCC48>": 2782,
      "<F6B044EE>": 3039,
      "<52603A9C>": 0
    },
    {
      "$id": 105,
      "<DBEA0DF4>": "<2C25D3C3>",
      "<A815E3A7>": 139,
      "<03053E2C>": 406,
      "<E04C8806>": 657,
      "<5DDB3CD8>": 929,
      "<4EC0BC69>": 1178,
      "<7D1DE80F>": 1437,
      "<B138A4D8>": 1697,
      "<CF46B266>": 1966,
      "<78873410>": 2247,
      "<532A2A64>": 2519,
      "<E64DCC48>": 2783,
      "<F6B044EE>": 3040,
      "<52603A9C>": 0
    },
    {
      "$id": 106,
      "<DBEA0DF4>": "<D564C3D3>",
      "<A815E3A7>": 140,
      "<03053E2C>": 407,
      "<E04C8806>": 658,
      "<5DDB3CD8>": 930,
      "<4EC0BC69>": 1179,
      "<7D1DE80F>": 1438,
      "<B138A4D8>": 1698,
      "<CF46B266>": 1967,
      "<78873410>": 2248,
      "<532A2A64>": 2520,
      "<E64DCC48>": 2784,
      "<F6B044EE>": 3041,
      "<52603A9C>": 0
    },
    {
      "$id": 107,
      "<DBEA0DF4>": "<7018EE37>",
      "<A815E3A7>": 141,
      "<03053E2C>": 408,
      "<E04C8806>": 659,
      "<5DDB3CD8>": 931,
      "<4EC0BC69>": 1180,
      "<7D1DE80F>": 1439,
      "<B138A4D8>": 1699,
      "<CF46B266>": 1968,
      "<78873410>": 2249,
      "<532A2A64>": 2521,
      "<E64DCC48>": 2785,
      "<F6B044EE>": 3042,
      "<52603A9C>": 0
    },
    {
      "$id": 108,
      "<DBEA0DF4>": "<BB6CEFFE>",
      "<A815E3A7>": 142,
      "<03053E2C>": 409,
      "<E04C8806>": 660,
      "<5DDB3CD8>": 932,
      "<4EC0BC69>": 1181,
      "<7D1DE80F>": 1440,
      "<B138A4D8>": 1700,
      "<CF46B266>": 1969,
      "<78873410>": 2250,
      "<532A2A64>": 2522,
      "<E64DCC48>": 2786,
      "<F6B044EE>": 3043,
      "<52603A9C>": 0
    },
    {
      "$id": 109,
      "<DBEA0DF4>": "<79E5426A>",
      "<A815E3A7>": 143,
      "<03053E2C>": 410,
      "<E04C8806>": 661,
      "<5DDB3CD8>": 939,
      "<4EC0BC69>": 1182,
      "<7D1DE80F>": 1441,
      "<B138A4D8>": 1701,
      "<CF46B266>": 1970,
      "<78873410>": 2251,
      "<532A2A64>": 2523,
      "<E64DCC48>": 2787,
      "<F6B044EE>": 3044,
      "<52603A9C>": 0
    },
    {
      "$id": 110,
      "<DBEA0DF4>": "<DCE5DA94>",
      "<A815E3A7>": 144,
      "<03053E2C>": 411,
      "<E04C8806>": 662,
      "<5DDB3CD8>": 940,
      "<4EC0BC69>": 1183,
      "<7D1DE80F>": 1442,
      "<B138A4D8>": 1702,
      "<CF46B266>": 1971,
      "<78873410>": 2252,
      "<532A2A64>": 2524,
      "<E64DCC48>": 2788,
      "<F6B044EE>": 3045,
      "<52603A9C>": 0
    },
    {
      "$id": 111,
      "<DBEA0DF4>": "<9151DDC4>",
      "<A815E3A7>": 145,
      "<03053E2C>": 412,
      "<E04C8806>": 663,
      "<5DDB3CD8>": 941,
      "<4EC0BC69>": 1184,
      "<7D1DE80F>": 1443,
      "<B138A4D8>": 1703,
      "<CF46B266>": 1972,
      "<78873410>": 2253,
      "<532A2A64>": 2525,
      "<E64DCC48>": 2789,
      "<F6B044EE>": 3046,
      "<52603A9C>": 0
    },
    {
      "$id": 112,
      "<DBEA0DF4>": "<76C9C359>",
      "<A815E3A7>": 146,
      "<03053E2C>": 419,
      "<E04C8806>": 664,
      "<5DDB3CD8>": 942,
      "<4EC0BC69>": 1185,
      "<7D1DE80F>": 1444,
      "<B138A4D8>": 1704,
      "<CF46B266>": 1979,
      "<78873410>": 2254,
      "<532A2A64>": 2526,
      "<E64DCC48>": 2796,
      "<F6B044EE>": 3053,
      "<52603A9C>": 0
    },
    {
      "$id": 113,
      "<DBEA0DF4>": "<1F157A35>",
      "<A815E3A7>": 147,
      "<03053E2C>": 420,
      "<E04C8806>": 665,
      "<5DDB3CD8>": 943,
      "<4EC0BC69>": 1186,
      "<7D1DE80F>": 1445,
      "<B138A4D8>": 1705,
      "<CF46B266>": 1980,
      "<78873410>": 2255,
      "<532A2A64>": 2527,
      "<E64DCC48>": 2797,
      "<F6B044EE>": 3054,
      "<52603A9C>": 0
    },
    {
      "$id": 114,
      "<DBEA0DF4>": "<4CAB2AD5>",
      "<A815E3A7>": 148,
      "<03053E2C>": 421,
      "<E04C8806>": 666,
      "<5DDB3CD8>": 944,
      "<4EC0BC69>": 1187,
      "<7D1DE80F>": 1446,
      "<B138A4D8>": 1706,
      "<CF46B266>": 1981,
      "<78873410>": 2256,
      "<532A2A64>": 2528,
      "<E64DCC48>": 2798,
      "<F6B044EE>": 3055,
      "<52603A9C>": 0
    },
    {
      "$id": 115,
      "<DBEA0DF4>": "<0C6510A8>",
      "<A815E3A7>": 149,
      "<03053E2C>": 422,
      "<E04C8806>": 667,
      "<5DDB3CD8>": 945,
      "<4EC0BC69>": 1188,
      "<7D1DE80F>": 1447,
      "<B138A4D8>": 1707,
      "<CF46B266>": 1982,
      "<78873410>": 2257,
      "<532A2A64>": 2535,
      "<E64DCC48>": 2799,
      "<F6B044EE>": 3056,
      "<52603A9C>": 0
    },
    {
      "$id": 116,
      "<DBEA0DF4>": "<7A22DE3D>",
      "<A815E3A7>": 150,
      "<03053E2C>": 423,
      "<E04C8806>": 668,
      "<5DDB3CD8>": 946,
      "<4EC0BC69>": 1189,
      "<7D1DE80F>": 1448,
      "<B138A4D8>": 1708,
      "<CF46B266>": 1983,
      "<78873410>": 2258,
      "<532A2A64>": 2536,
      "<E64DCC48>": 2800,
      "<F6B044EE>": 3057,
      "<52603A9C>": 0
    },
    {
      "$id": 117,
      "<DBEA0DF4>": "<FFD74FDB>",
      "<A815E3A7>": 151,
      "<03053E2C>": 424,
      "<E04C8806>": 669,
      "<5DDB3CD8>": 947,
      "<4EC0BC69>": 1190,
      "<7D1DE80F>": 1449,
      "<B138A4D8>": 1709,
      "<CF46B266>": 1984,
      "<78873410>": 2259,
      "<532A2A64>": 2537,
      "<E64DCC48>": 2801,
      "<F6B044EE>": 3058,
      "<52603A9C>": 0
    },
    {
      "$id": 118,
      "<DBEA0DF4>": "<854A2E33>",
      "<A815E3A7>": 158,
      "<03053E2C>": 425,
      "<E04C8806>": 676,
      "<5DDB3CD8>": 948,
      "<4EC0BC69>": 1197,
      "<7D1DE80F>": 1456,
      "<B138A4D8>": 1716,
      "<CF46B266>": 1985,
      "<78873410>": 2260,
      "<532A2A64>": 2538,
      "<E64DCC48>": 2802,
      "<F6B044EE>": 3059,
      "<52603A9C>": 0
    },
    {
      "$id": 119,
      "<DBEA0DF4>": "<EA2A31C8>",
      "<A815E3A7>": 159,
      "<03053E2C>": 426,
      "<E04C8806>": 677,
      "<5DDB3CD8>": 949,
      "<4EC0BC69>": 1198,
      "<7D1DE80F>": 1457,
      "<B138A4D8>": 1717,
      "<CF46B266>": 1986,
      "<78873410>": 2261,
      "<532A2A64>": 2539,
      "<E64DCC48>": 2803,
      "<F6B044EE>": 3060,
      "<52603A9C>": 0
    },
    {
      "$id": 120,
      "<DBEA0DF4>": "<664D5F27>",
      "<A815E3A7>": 160,
      "<03053E2C>": 427,
      "<E04C8806>": 678,
      "<5DDB3CD8>": 950,
      "<4EC0BC69>": 1199,
      "<7D1DE80F>": 1458,
      "<B138A4D8>": 1718,
      "<CF46B266>": 1987,
      "<78873410>": 2262,
      "<532A2A64>": 2540,
      "<E64DCC48>": 2804,
      "<F6B044EE>": 3061,
      "<52603A9C>": 0
    },
    {
      "$id": 121,
      "<DBEA0DF4>": "<69684EF3>",
      "<A815E3A7>": 161,
      "<03053E2C>": 428,
      "<E04C8806>": 679,
      "<5DDB3CD8>": 951,
      "<4EC0BC69>": 1200,
      "<7D1DE80F>": 1459,
      "<B138A4D8>": 1719,
      "<CF46B266>": 1988,
      "<78873410>": 2269,
      "<532A2A64>": 2541,
      "<E64DCC48>": 2805,
      "<F6B044EE>": 3062,
      "<52603A9C>": 0
    },
    {
      "$id": 122,
      "<DBEA0DF4>": "<BCD53159>",
      "<A815E3A7>": 162,
      "<03053E2C>": 429,
      "<E04C8806>": 680,
      "<5DDB3CD8>": 952,
      "<4EC0BC69>": 1201,
      "<7D1DE80F>": 1460,
      "<B138A4D8>": 1720,
      "<CF46B266>": 1989,
      "<78873410>": 2270,
      "<532A2A64>": 2542,
      "<E64DCC48>": 2806,
      "<F6B044EE>": 3063,
      "<52603A9C>": 0
    },
    {
      "$id": 123,
      "<DBEA0DF4>": "<FCD51274>",
      "<A815E3A7>": 163,
      "<03053E2C>": 430,
      "<E04C8806>": 681,
      "<5DDB3CD8>": 953,
      "<4EC0BC69>": 1202,
      "<7D1DE80F>": 1461,
      "<B138A4D8>": 1721,
      "<CF46B266>": 1990,
      "<78873410>": 2271,
      "<532A2A64>": 2543,
      "<E64DCC48>": 2807,
      "<F6B044EE>": 3064,
      "<52603A9C>": 0
    },
    {
      "$id": 124,
      "<DBEA0DF4>": "<7D19E253>",
      "<A815E3A7>": 164,
      "<03053E2C>": 431,
      "<E04C8806>": 682,
      "<5DDB3CD8>": 960,
      "<4EC0BC69>": 1203,
      "<7D1DE80F>": 1462,
      "<B138A4D8>": 1722,
      "<CF46B266>": 1991,
      "<78873410>": 2272,
      "<532A2A64>": 2544,
      "<E64DCC48>": 2808,
      "<F6B044EE>": 3065,
      "<52603A9C>": 0
    },
    {
      "$id": 125,
      "<DBEA0DF4>": "<26D13400>",
      "<A815E3A7>": 165,
      "<03053E2C>": 432,
      "<E04C8806>": 683,
      "<5DDB3CD8>": 961,
      "<4EC0BC69>": 1204,
      "<7D1DE80F>": 1463,
      "<B138A4D8>": 1723,
      "<CF46B266>": 1992,
      "<78873410>": 2273,
      "<532A2A64>": 2545,
      "<E64DCC48>": 2809,
      "<F6B044EE>": 3066,
      "<52603A9C>": 0
    },
    {
      "$id": 126,
      "<DBEA0DF4>": "<509EEFE9>",
      "<A815E3A7>": 166,
      "<03053E2C>": 433,
      "<E04C8806>": 684,
      "<5DDB3CD8>": 962,
      "<4EC0BC69>": 1205,
      "<7D1DE80F>": 1464,
      "<B138A4D8>": 1724,
      "<CF46B266>": 1993,
      "<78873410>": 2274,
      "<532A2A64>": 2546,
      "<E64DCC48>": 2810,
      "<F6B044EE>": 3067,
      "<52603A9C>": 0
    },
    {
      "$id": 127,
      "<DBEA0DF4>": "<65FEE1AB>",
      "<A815E3A7>": 167,
      "<03053E2C>": 440,
      "<E04C8806>": 685,
      "<5DDB3CD8>": 963,
      "<4EC0BC69>": 1206,
      "<7D1DE80F>": 1465,
      "<B138A4D8>": 1725,
      "<CF46B266>": 2000,
      "<78873410>": 2275,
      "<532A2A64>": 2547,
      "<E64DCC48>": 2817,
      "<F6B044EE>": 3074,
      "<52603A9C>": 0
    },
    {
      "$id": 128,
      "<DBEA0DF4>": "<41A432AC>",
      "<A815E3A7>": 168,
      "<03053E2C>": 441,
      "<E04C8806>": 686,
      "<5DDB3CD8>": 964,
      "<4EC0BC69>": 1207,
      "<7D1DE80F>": 1466,
      "<B138A4D8>": 1726,
      "<CF46B266>": 2001,
      "<78873410>": 2276,
      "<532A2A64>": 2548,
      "<E64DCC48>": 2818,
      "<F6B044EE>": 3075,
      "<52603A9C>": 0
    },
    {
      "$id": 129,
      "<DBEA0DF4>": "<25A41144>",
      "<A815E3A7>": 169,
      "<03053E2C>": 442,
      "<E04C8806>": 687,
      "<5DDB3CD8>": 965,
      "<4EC0BC69>": 1208,
      "<7D1DE80F>": 1467,
      "<B138A4D8>": 1727,
      "<CF46B266>": 2002,
      "<78873410>": 2277,
      "<532A2A64>": 2549,
      "<E64DCC48>": 2819,
      "<F6B044EE>": 3076,
      "<52603A9C>": 0
    },
    {
      "$id": 130,
      "<DBEA0DF4>": "<B50AD16F>",
      "<A815E3A7>": 170,
      "<03053E2C>": 443,
      "<E04C8806>": 688,
      "<5DDB3CD8>": 966,
      "<4EC0BC69>": 1209,
      "<7D1DE80F>": 1468,
      "<B138A4D8>": 1728,
      "<CF46B266>": 2003,
      "<78873410>": 2278,
      "<532A2A64>": 2556,
      "<E64DCC48>": 2820,
      "<F6B044EE>": 3077,
      "<52603A9C>": 0
    },
    {
      "$id": 131,
      "<DBEA0DF4>": "<F72EFAFD>",
      "<A815E3A7>": 171,
      "<03053E2C>": 444,
      "<E04C8806>": 689,
      "<5DDB3CD8>": 967,
      "<4EC0BC69>": 1210,
      "<7D1DE80F>": 1469,
      "<B138A4D8>": 1729,
      "<CF46B266>": 2004,
      "<78873410>": 2279,
      "<532A2A64>": 2557,
      "<E64DCC48>": 2821,
      "<F6B044EE>": 3078,
      "<52603A9C>": 0
    },
    {
      "$id": 132,
      "<DBEA0DF4>": "<D0050325>",
      "<A815E3A7>": 172,
      "<03053E2C>": 445,
      "<E04C8806>": 690,
      "<5DDB3CD8>": 968,
      "<4EC0BC69>": 1211,
      "<7D1DE80F>": 1470,
      "<B138A4D8>": 1730,
      "<CF46B266>": 2005,
      "<78873410>": 2280,
      "<532A2A64>": 2558,
      "<E64DCC48>": 2822,
      "<F6B044EE>": 3079,
      "<52603A9C>": 0
    },
    {
      "$id": 133,
      "<DBEA0DF4>": "<9D1A41E3>",
      "<A815E3A7>": 179,
      "<03053E2C>": 446,
      "<E04C8806>": 697,
      "<5DDB3CD8>": 969,
      "<4EC0BC69>": 1218,
      "<7D1DE80F>": 1477,
      "<B138A4D8>": 1737,
      "<CF46B266>": 2006,
      "<78873410>": 2281,
      "<532A2A64>": 2559,
      "<E64DCC48>": 2823,
      "<F6B044EE>": 3080,
      "<52603A9C>": 0
    },
    {
      "$id": 134,
      "<DBEA0DF4>": "<D2599785>",
      "<A815E3A7>": 180,
      "<03053E2C>": 447,
      "<E04C8806>": 698,
      "<5DDB3CD8>": 970,
      "<4EC0BC69>": 1219,
      "<7D1DE80F>": 1478,
      "<B138A4D8>": 1738,
      "<CF46B266>": 2007,
      "<78873410>": 2282,
      "<532A2A64>": 2560,
      "<E64DCC48>": 2824,
      "<F6B044EE>": 3081,
      "<52603A9C>": 0
    },
    {
      "$id": 135,
      "<DBEA0DF4>": "<74F33DB2>",
      "<A815E3A7>": 181,
      "<03053E2C>": 448,
      "<E04C8806>": 699,
      "<5DDB3CD8>": 971,
      "<4EC0BC69>": 1220,
      "<7D1DE80F>": 1479,
      "<B138A4D8>": 1739,
      "<CF46B266>": 2008,
      "<78873410>": 2283,
      "<532A2A64>": 2561,
      "<E64DCC48>": 2825,
      "<F6B044EE>": 3082,
      "<52603A9C>": 0
    },
    {
      "$id": 136,
      "<DBEA0DF4>": "<D154826E>",
      "<A815E3A7>": 182,
      "<03053E2C>": 449,
      "<E04C8806>": 700,
      "<5DDB3CD8>": 972,
      "<4EC0BC69>": 1221,
      "<7D1DE80F>": 1480,
      "<B138A4D8>": 1740,
      "<CF46B266>": 2009,
      "<78873410>": 2290,
      "<532A2A64>": 2562,
      "<E64DCC48>": 2826,
      "<F6B044EE>": 3083,
      "<52603A9C>": 0
    },
    {
      "$id": 137,
      "<DBEA0DF4>": "<CE58B101>",
      "<A815E3A7>": 183,
      "<03053E2C>": 450,
      "<E04C8806>": 701,
      "<5DDB3CD8>": 973,
      "<4EC0BC69>": 1222,
      "<7D1DE80F>": 1481,
      "<B138A4D8>": 1741,
      "<CF46B266>": 2010,
      "<78873410>": 2291,
      "<532A2A64>": 2563,
      "<E64DCC48>": 2827,
      "<F6B044EE>": 3084,
      "<52603A9C>": 0
    },
    {
      "$id": 138,
      "<DBEA0DF4>": "<981891F4>",
      "<A815E3A7>": 184,
      "<03053E2C>": 451,
      "<E04C8806>": 702,
      "<5DDB3CD8>": 974,
      "<4EC0BC69>": 1223,
      "<7D1DE80F>": 1482,
      "<B138A4D8>": 1742,
      "<CF46B266>": 2011,
      "<78873410>": 2292,
      "<532A2A64>": 2564,
      "<E64DCC48>": 2828,
      "<F6B044EE>": 3085,
      "<52603A9C>": 0
    },
    {
      "$id": 139,
      "<DBEA0DF4>": "<38A47CD7>",
      "<A815E3A7>": 185,
      "<03053E2C>": 452,
      "<E04C8806>": 703,
      "<5DDB3CD8>": 0,
      "<4EC0BC69>": 1224,
      "<7D1DE80F>": 1483,
      "<B138A4D8>": 1743,
      "<CF46B266>": 2012,
      "<78873410>": 2293,
      "<532A2A64>": 2565,
      "<E64DCC48>": 2829,
      "<F6B044EE>": 3086,
      "<52603A9C>": 0
    },
    {
      "$id": 140,
      "<DBEA0DF4>": "<D363C3C4>",
      "<A815E3A7>": 186,
      "<03053E2C>": 453,
      "<E04C8806>": 704,
      "<5DDB3CD8>": 0,
      "<4EC0BC69>": 1225,
      "<7D1DE80F>": 1484,
      "<B138A4D8>": 1744,
      "<CF46B266>": 2013,
      "<78873410>": 2294,
      "<532A2A64>": 2566,
      "<E64DCC48>": 2830,
      "<F6B044EE>": 3087,
      "<52603A9C>": 0
    },
    {
      "$id": 141,
      "<DBEA0DF4>": "<DD017F82>",
      "<A815E3A7>": 187,
      "<03053E2C>": 454,
      "<E04C8806>": 705,
      "<5DDB3CD8>": 0,
      "<4EC0BC69>": 1226,
      "<7D1DE80F>": 1485,
      "<B138A4D8>": 1745,
      "<CF46B266>": 2014,
      "<78873410>": 2295,
      "<532A2A64>": 2567,
      "<E64DCC48>": 2831,
      "<F6B044EE>": 3088,
      "<52603A9C>": 0
    },
    {
      "$id": 142,
      "<DBEA0DF4>": "<110AB4A4>",
      "<A815E3A7>": 188,
      "<03053E2C>": 0,
      "<E04C8806>": 706,
      "<5DDB3CD8>": 0,
      "<4EC0BC69>": 1227,
      "<7D1DE80F>": 1486,
      "<B138A4D8>": 1746,
      "<CF46B266>": 2021,
      "<78873410>": 2296,
      "<532A2A64>": 2568,
      "<E64DCC48>": 0,
      "<F6B044EE>": 0,
      "<52603A9C>": 0
    },
    {
      "$id": 143,
      "<DBEA0DF4>": "<F85AD572>",
      "<A815E3A7>": 189,
      "<03053E2C>": 0,
      "<E04C8806>": 707,
      "<5DDB3CD8>": 0,
      "<4EC0BC69>": 1228,
      "<7D1DE80F>": 1487,
      "<B138A4D8>": 1747,
      "<CF46B266>": 2022,
      "<78873410>": 2297,
      "<532A2A64>": 2569,
      "<E64DCC48>": 0,
      "<F6B044EE>": 0,
      "<52603A9C>": 0
    },
    {
      "$id": 144,
      "<DBEA0DF4>": "<1F2506A4>",
      "<A815E3A7>": 190,
      "<03053E2C>": 0,
      "<E04C8806>": 708,
      "<5DDB3CD8>": 0,
      "<4EC0BC69>": 1229,
      "<7D1DE80F>": 1488,
      "<B138A4D8>": 1748,
      "<CF46B266>": 2023,
      "<78873410>": 2298,
      "<532A2A64>": 2570,
      "<E64DCC48>": 0,
      "<F6B044EE>": 0,
      "<52603A9C>": 0
    },
    {
      "$id": 145,
      "<DBEA0DF4>": "<BB64CCE8>",
      "<A815E3A7>": 191,
      "<03053E2C>": 0,
      "<E04C8806>": 709,
      "<5DDB3CD8>": 0,
      "<4EC0BC69>": 1230,
      "<7D1DE80F>": 1489,
      "<B138A4D8>": 1749,
      "<CF46B266>": 2024,
      "<78873410>": 2299,
      "<532A2A64>": 0,
      "<E64DCC48>": 0,
      "<F6B044EE>": 0,
      "<52603A9C>": 0
    },
    {
      "$id": 146,
      "<DBEA0DF4>": "<4B4C24FB>",
      "<A815E3A7>": 192,
      "<03053E2C>": 0,
      "<E04C8806>": 710,
      "<5DDB3CD8>": 0,
      "<4EC0BC69>": 1231,
      "<7D1DE80F>": 1490,
      "<B138A4D8>": 1750,
      "<CF46B266>": 2025,
      "<78873410>": 2300,
      "<532A2A64>": 0,
      "<E64DCC48>": 0,
      "<F6B044EE>": 0,
      "<52603A9C>": 0
    },
    {
      "$id": 147,
      "<DBEA0DF4>": "<A7A6A731>",
      "<A815E3A7>": 193,
      "<03053E2C>": 0,
      "<E04C8806>": 711,
      "<5DDB3CD8>": 0,
      "<4EC0BC69>": 1232,
      "<7D1DE80F>": 1491,
      "<B138A4D8>": 1751,
      "<CF46B266>": 2026,
      "<78873410>": 2301,
      "<532A2A64>": 0,
      "<E64DCC48>": 0,
      "<F6B044EE>": 0,
      "<52603A9C>": 0
    },
    {
      "$id": 148,
      "<DBEA0DF4>": "<9149D217>",
      "<A815E3A7>": 0,
      "<03053E2C>": 0,
      "<E04C8806>": 0,
      "<5DDB3CD8>": 0,
      "<4EC0BC69>": 0,
      "<7D1DE80F>": 0,
      "<B138A4D8>": 0,
      "<CF46B266>": 2027,
      "<78873410>": 2302,
      "<532A2A64>": 0,
      "<E64DCC48>": 0,
      "<F6B044EE>": 0,
      "<52603A9C>": 0
    },
    {
      "$id": 149,
      "<DBEA0DF4>": "<0AD8B3BD>",
      "<A815E3A7>": 0,
      "<03053E2C>": 0,
      "<E04C8806>": 0,
      "<5DDB3CD8>": 0,
      "<4EC0BC69>": 0,
      "<7D1DE80F>": 0,
      "<B138A4D8>": 0,
      "<CF46B266>": 2028,
      "<78873410>": 2303,
      "<532A2A64>": 0,
      "<E64DCC48>": 0,
      "<F6B044EE>": 0,
      "<52603A9C>": 0
    },
    {
      "$id": 150,
      "<DBEA0DF4>": "<58500C9B>",
      "<A815E3A7>": 0,
      "<03053E2C>": 0,
      "<E04C8806>": 0,
      "<5DDB3CD8>": 0,
      "<4EC0BC69>": 0,
      "<7D1DE80F>": 0,
      "<B138A4D8>": 0,
      "<CF46B266>": 2029,
      "<78873410>": 2304,
      "<532A2A64>": 0,
      "<E64DCC48>": 0,
      "<F6B044EE>": 0,
      "<52603A9C>": 0
    },
    {
      "$id": 151,
      "<DBEA0DF4>": "<75DB74E0>",
      "<A815E3A7>": 0,
      "<03053E2C>": 0,
      "<E04C8806>": 0,
      "<5DDB3CD8>": 0,
      "<4EC0BC69>": 0,
      "<7D1DE80F>": 0,
      "<B138A4D8>": 0,
      "<CF46B266>": 2030,
      "<78873410>": 0,
      "<532A2A64>": 0,
      "<E64DCC48>": 0,
      "<F6B044EE>": 0,
      "<52603A9C>": 0
    },
    {
      "$id": 152,
      "<DBEA0DF4>": "<0D81BB79>",
      "<A815E3A7>": 0,
      "<03053E2C>": 0,
      "<E04C8806>": 0,
      "<5DDB3CD8>": 0,
      "<4EC0BC69>": 0,
      "<7D1DE80F>": 0,
      "<B138A4D8>": 0,
      "<CF46B266>": 2031,
      "<78873410>": 0,
      "<532A2A64>": 0,
      "<E64DCC48>": 0,
      "<F6B044EE>": 0,
      "<52603A9C>": 0
    },
    {
      "$id": 153,
      "<DBEA0DF4>": "<A4F4AF95>",
      "<A815E3A7>": 0,
      "<03053E2C>": 0,
      "<E04C8806>": 0,
      "<5DDB3CD8>": 0,
      "<4EC0BC69>": 0,
      "<7D1DE80F>": 0,
      "<B138A4D8>": 0,
      "<CF46B266>": 2032,
      "<78873410>": 0,
      "<532A2A64>": 0,
      "<E64DCC48>": 0,
      "<F6B044EE>": 0,
      "<52603A9C>": 0
    },
    {
      "$id": 154,
      "<DBEA0DF4>": "<1554F286>",
      "<A815E3A7>": 0,
      "<03053E2C>": 0,
      "<E04C8806>": 0,
      "<5DDB3CD8>": 0,
      "<4EC0BC69>": 0,
      "<7D1DE80F>": 0,
      "<B138A4D8>": 0,
      "<CF46B266>": 2033,
      "<78873410>": 0,
      "<532A2A64>": 0,
      "<E64DCC48>": 0,
      "<F6B044EE>": 0,
      "<52603A9C>": 0
    },
    {
      "$id": 155,
      "<DBEA0DF4>": "<1C117135>",
      "<A815E3A7>": 0,
      "<03053E2C>": 0,
      "<E04C8806>": 0,
      "<5DDB3CD8>": 0,
      "<4EC0BC69>": 0,
      "<7D1DE80F>": 0,
      "<B138A4D8>": 0,
      "<CF46B266>": 2034,
      "<78873410>": 0,
      "<532A2A64>": 0,
      "<E64DCC48>": 0,
      "<F6B044EE>": 0,
      "<52603A9C>": 0
    },
    {
      "$id": 156,
      "<DBEA0DF4>": "<980360E4>",
      "<A815E3A7>": 0,
      "<03053E2C>": 0,
      "<E04C8806>": 0,
      "<5DDB3CD8>": 0,
      "<4EC0BC69>": 0,
      "<7D1DE80F>": 0,
      "<B138A4D8>": 0,
      "<CF46B266>": 2035,
      "<78873410>": 0,
      "<532A2A64>": 0,
      "<E64DCC48>": 0,
      "<F6B044EE>": 0,
      "<52603A9C>": 0
    }
  ]
}