{
  "schema": [
    {
      "name": "label",
      "type": 9
    },
    {
      "name": "style",
      "type": 2
    },
    {
      "name": "name",
      "type": 7
    }
  ],
  "rows": [
    {
      "$id": 1,
      "label": "qev091304_MSG0001",
      "style": 0,
      "name": "This one's pulled out of the\nground just like the others.[ST:wait ]"
    },
    {
      "$id": 2,
      "label": "qev091304_JNK0010",
      "style": 4,
      "name": "Speculate"
    },
    {
      "$id": 3,
      "label": "qev091304_SEL0011",
      "style": 3,
      "name": "Say that something is obviously\ndigging the data probes up."
    },
    {
      "$id": 4,
      "label": "qev091304_JNK0020",
      "style": 4,
      "name": "Correct"
    },
    {
      "$id": 5,
      "label": "qev091304_SEL0021",
      "style": 3,
      "name": "Remind Fog Christoph that you have\nalready checked this location."
    },
    {
      "$id": 6,
      "label": "qev091304_MSG0002",
      "style": 0,
      "name": "Right?[ST:wait ]"
    },
    {
      "$id": 7,
      "label": "qev091304_MSG0003",
      "style": 0,
      "name": "...Wait. Haven't we been here already?[ST:wait ]"
    },
    {
      "$id": 8,
      "label": "qev091304_MSG0004",
      "style": 0,
      "name": "Huh?[ST:wait ]"
    },
    {
      "$id": 9,
      "label": "qev091304_MSG0005",
      "style": 0,
      "name": "Huh. You're right. This\nIS where we started.[ST:wait ]"
    },
    {
      "$id": 10,
      "label": "qev091304_MSG0006",
      "style": 0,
      "name": "Apologies. That's my mistake.[ST:wait ]"
    },
    {
      "$id": 11,
      "label": "qev091304_MSG0007",
      "style": 0,
      "name": "My brother was always\nyelling at me to focus.[ST:wait ]"
    },
    {
      "$id": 12,
      "label": "qev091304_MSG0007_02",
      "style": 0,
      "name": "He used to say the only mistakes\nI made were stupid ones.[ST:wait ]"
    },
    {
      "$id": 13,
      "label": "qev091304_MSG0008",
      "style": 0,
      "name": "Guess I haven't made much\nprogress on that front.[ST:wait ]"
    },
    {
      "$id": 14,
      "label": "qev091304_JNK0030",
      "style": 4,
      "name": "Comfort"
    },
    {
      "$id": 15,
      "label": "qev091304_SEL0031",
      "style": 3,
      "name": "Remind Fog Christoph\nthat no one is perfect."
    },
    {
      "$id": 16,
      "label": "qev091304_JNK0040",
      "style": 4,
      "name": "Scold"
    },
    {
      "$id": 17,
      "label": "qev091304_SEL0041",
      "style": 3,
      "name": "Yell at Fog Christoph to\nget his act together."
    },
    {
      "$id": 18,
      "label": "qev091304_JNK0050",
      "style": 4,
      "name": "Counsel"
    },
    {
      "$id": 19,
      "label": "qev091304_SEL0051",
      "style": 3,
      "name": "Tell Fog Christoph that all progress\nis built on such mistakes."
    },
    {
      "$id": 20,
      "label": "qev091304_MSG0009",
      "style": 0,
      "name": "Oh, uh, thanks. I\nappreciate your patience.[ST:wait ]"
    },
    {
      "$id": 21,
      "label": "qev091304_MSG0010",
      "style": 0,
      "name": "I promise it won't happen again.[ST:wait ]"
    },
    {
      "$id": 22,
      "label": "qev091304_MSG0011",
      "style": 0,
      "name": "You're right, of course. One mistake out\nhere could put our lives in danger.[ST:wait ]"
    },
    {
      "$id": 23,
      "label": "qev091304_MSG0012",
      "style": 0,
      "name": "You're very kind.[ST:wait ]"
    },
    {
      "$id": 24,
      "label": "qev091304_MSG0013",
      "style": 0,
      "name": "I'll add this to the list of\nmistakes I mull over in my\nhead before going to sleep.[ST:wait ]"
    },
    {
      "$id": 25,
      "label": "qev091304_MSG0014",
      "style": 0,
      "name": "...Okay.[ST:wait ]"
    },
    {
      "$id": 26,
      "label": "qev091304_MSG0015",
      "style": 0,
      "name": "Well, there's nothing else for us here.\nLet's head to our actual destination.[ST:wait ]"
    }
  ]
}