{
  "schema": [
    {
      "name": "label",
      "type": 9
    },
    {
      "name": "style",
      "type": 2
    },
    {
      "name": "name",
      "type": 7
    }
  ],
  "rows": [
    {
      "$id": 1,
      "label": "xs09110100_MSG0001",
      "style": 0,
      "name": " [ST:wait ]"
    },
    {
      "$id": 2,
      "label": "xs09110100_MSG0002",
      "style": 0,
      "name": "Morning, Sleeping Beauty.[ST:wait ]\n"
    },
    {
      "$id": 3,
      "label": "xs09110100_MSG0003",
      "style": 0,
      "name": "Doug...? Is this...the Lifehold?[ST:wait ]\n"
    },
    {
      "$id": 4,
      "label": "xs09110100_MSG0004",
      "style": 0,
      "name": "New LA, buddy.[ST:wait ]\n"
    },
    {
      "$id": 5,
      "label": "xs09110100_MSG0005",
      "style": 0,
      "name": "Sorry, no real body just yet—they saved your mim before\nit shut down. Too bad, eh? Better luck next time you die.[ST:wait ]\n"
    },
    {
      "$id": 6,
      "label": "xs09110100_MSG0006",
      "style": 0,
      "name": "I see...[ST:wait ]\n"
    },
    {
      "$id": 7,
      "label": "xs09110100_MSG0007",
      "style": 0,
      "name": "Doug, it's...it's all my fault...[ST:wait ]\n"
    },
    {
      "$id": 8,
      "label": "xs09110100_MSG0008",
      "style": 0,
      "name": "Save it. Just rest.[ST:wait ]\n"
    },
    {
      "$id": 9,
      "label": "xs09110100_MSG0009",
      "style": 0,
      "name": ""
    },
    {
      "$id": 10,
      "label": "xs09110100_MSG0010",
      "style": 0,
      "name": "Elma.[ST:wait ]\n"
    },
    {
      "$id": 11,
      "label": "xs09110100_MSG0011",
      "style": 0,
      "name": "Doug. You beat us here.[ST:wait ]\n"
    },
    {
      "$id": 12,
      "label": "xs09110100_MSG0012",
      "style": 0,
      "name": "So...how's he doing?[ST:wait ]\n"
    },
    {
      "$id": 13,
      "label": "xs09110100_MSG0013",
      "style": 0,
      "name": "He'll be up and around in no time.[ST:wait ]\n"
    },
    {
      "$id": 14,
      "label": "xs09110100_MSG0014",
      "style": 0,
      "name": "Why don't you go take a look for yourself, say hi?[ST:wait ]\n"
    },
    {
      "$id": 15,
      "label": "xs09110100_MSG0015",
      "style": 0,
      "name": "Thanks.[ST:wait ]\n"
    },
    {
      "$id": 16,
      "label": "xs09110100_MSG0016",
      "style": 0,
      "name": "Doug...we need to talk. Can you spare a minute?[ST:wait ]\n"
    },
    {
      "$id": 17,
      "label": "xs09110100_MSG0017",
      "style": 0,
      "name": "Of course.[ST:wait ]\n"
    },
    {
      "$id": 18,
      "label": "xs09110100_MSG0018",
      "style": 0,
      "name": "It's...about Lao.[ST:wait ]\n"
    },
    {
      "$id": 19,
      "label": "xs09110100_MSG0019",
      "style": 0,
      "name": "I have a suspicion...well, it's more than a suspicion.[ST:wait ]\n"
    },
    {
      "$id": 20,
      "label": "xs09110100_MSG0020",
      "style": 0,
      "name": "Let's hear it.[ST:wait ]\n"
    },
    {
      "$id": 21,
      "label": "xs09110100_MSG0021",
      "style": 0,
      "name": "The Ganglion were struggling to retrieve\nthat alien mech—the Vita.[ST:wait ]\n"
    },
    {
      "$id": 22,
      "label": "xs09110100_MSG0022",
      "style": 0,
      "name": "Lao suggested we go after it. He even planned the mission.[ST:wait ]\n"
    },
    {
      "$id": 23,
      "label": "xs09110100_MSG0023",
      "style": 0,
      "name": "So we extract it...[ST:wait ]\n"
    },
    {
      "$id": 24,
      "label": "xs09110100_MSG0024",
      "style": 0,
      "name": "and the Ganglion know exactly where it is when they\ncome for it, with Lao's team away from guard duty.[ST:wait ]\n"
    },
    {
      "$id": 25,
      "label": "xs09110100_MSG0025",
      "style": 0,
      "name": "Oh boy...[ST:wait ]\n"
    },
    {
      "$id": 26,
      "label": "xs09110100_MSG0026",
      "style": 0,
      "name": "And this last mission—he gave us coordinates\nfor a Lifehold unit he found.[ST:wait ]\n"
    },
    {
      "$id": 27,
      "label": "xs09110100_MSG0027",
      "style": 0,
      "name": "Turned out to be a Ganglion ambush.[ST:wait ]\n"
    },
    {
      "$id": 28,
      "label": "xs09110100_MSG0028",
      "style": 0,
      "name": "It's too much to be a coincidence, Doug.[ST:wait ]\n"
    },
    {
      "$id": 29,
      "label": "xs09110100_MSG0029",
      "style": 0,
      "name": "Well...what do you think, Rook?\nYou think he's a spy?[ST:wait ]\n"
    },
    {
      "$id": 30,
      "label": "xs09110100_JNK0010",
      "style": 4,
      "name": "Nod"
    },
    {
      "$id": 31,
      "label": "xs09110100_SEL0011",
      "style": 3,
      "name": "Agree with Elma."
    },
    {
      "$id": 32,
      "label": "xs09110100_JNK0020",
      "style": 4,
      "name": "Shake Your Head"
    },
    {
      "$id": 33,
      "label": "xs09110100_SEL0021",
      "style": 3,
      "name": "Show you still trust Lao."
    },
    {
      "$id": 34,
      "label": "xs09110100_MSG0030",
      "style": 0,
      "name": "Even if you're right, he saved our bacon plenty of times.[ST:wait ]\n"
    },
    {
      "$id": 35,
      "label": "xs09110100_MSG0031",
      "style": 0,
      "name": "We should at least give him a chance to explain himself.[ST:wait ]\n"
    },
    {
      "$id": 36,
      "label": "xs09110100_MSG0032",
      "style": 0,
      "name": "We owe him that much.[ST:wait ]\n"
    },
    {
      "$id": 37,
      "label": "xs09110100_MSG0033",
      "style": 0,
      "name": "Yeah, I guess you're right.[ST:wait ]\n"
    },
    {
      "$id": 38,
      "label": "xs09110100_MSG0034",
      "style": 0,
      "name": "Agreed—there must be some other explanation.[ST:wait ]\n"
    },
    {
      "$id": 39,
      "label": "xs09110100_MSG0035",
      "style": 0,
      "name": "Lao hates those xenos.[ST:wait ]\n"
    },
    {
      "$id": 40,
      "label": "xs09110100_MSG0036",
      "style": 0,
      "name": "He wouldn't sell us out—no way, no how.[ST:wait ]\n"
    },
    {
      "$id": 41,
      "label": "xs09110100_MSG0037",
      "style": 0,
      "name": "All right, Doug. I hear you.[ST:wait ]\n"
    },
    {
      "$id": 42,
      "label": "xs09110100_MSG0038",
      "style": 0,
      "name": "If you still trust him, then so will I.[ST:wait ]\n"
    },
    {
      "$id": 43,
      "label": "xs09110100_MSG0039",
      "style": 0,
      "name": "You're doing the right thing, Elma.[ST:wait ]\n"
    }
  ]
}