{
  "schema": [
    {
      "name": "label",
      "type": 9
    },
    {
      "name": "style",
      "type": 2
    },
    {
      "name": "name",
      "type": 7
    }
  ],
  "rows": [
    {
      "$id": 1,
      "label": "qev092104_MSG0001",
      "style": 0,
      "name": "Here, have a look. These are Mika and Fernand's Skells.[ST:wait ]\n"
    },
    {
      "$id": 2,
      "label": "qev092104_MSG0002",
      "style": 0,
      "name": "His is like yours, Camber—broken, but otherwise pretty clean.[ST:wait ]\n"
    },
    {
      "$id": 3,
      "label": "qev092104_MSG0003",
      "style": 0,
      "name": "That's a characteristic of the prototype weapon.[ST:wait ]\n"
    },
    {
      "$id": 4,
      "label": "qev092104_MSG0004",
      "style": 0,
      "name": "But look at Mika's.\nIt's smoking and covered in bullet holes...[ST:wait ]\n"
    },
    {
      "$id": 5,
      "label": "qev092104_MSG0005",
      "style": 0,
      "name": "You're right.[ST:wait ]\n"
    },
    {
      "$id": 6,
      "label": "qev092104_MSG0006",
      "style": 0,
      "name": "Which means...[ST:wait ]\n"
    },
    {
      "$id": 7,
      "label": "qev092104_JNK0010",
      "style": 4,
      "name": "Conclude"
    },
    {
      "$id": 8,
      "label": "qev092104_SEL0011",
      "style": 3,
      "name": "Say that Mika was attacked by an enemy."
    },
    {
      "$id": 9,
      "label": "qev092104_JNK0020",
      "style": 4,
      "name": "Guess"
    },
    {
      "$id": 10,
      "label": "qev092104_SEL0021",
      "style": 3,
      "name": "Surmise that Mika and Hannah\nmust have been fighting each other."
    },
    {
      "$id": 11,
      "label": "qev092104_MSG0007",
      "style": 0,
      "name": "It has to be. The Ganglion must have\nbeen drawn here by the explosion.[ST:wait ]\n"
    },
    {
      "$id": 12,
      "label": "qev092104_MSG0008",
      "style": 0,
      "name": "Mika and Hannah? That's crazy![ST:wait ]\n"
    },
    {
      "$id": 13,
      "label": "qev092104_MSG0009",
      "style": 0,
      "name": "I refuse to even consider that![ST:wait ]\n"
    },
    {
      "$id": 14,
      "label": "qev092104_MSG0010",
      "style": 0,
      "name": "I agree. Mika wouldn't do that.[ST:wait ]\n"
    },
    {
      "$id": 15,
      "label": "qev092104_MSG0011",
      "style": 0,
      "name": "I think the explosion drew the Ganglion's attention.[ST:wait ]\n"
    },
    {
      "$id": 16,
      "label": "qev092104_MSG0012",
      "style": 0,
      "name": "Those bastards![ST:wait ]\n"
    },
    {
      "$id": 17,
      "label": "qev092104_MSG0013",
      "style": 0,
      "name": "The girls had two damaged Skells,\nwhich would have made them easy prey.[ST:wait ]\n"
    },
    {
      "$id": 18,
      "label": "qev092104_MSG0014",
      "style": 0,
      "name": "So Mika's Skell was destroyed, and Hannah—[ST:wait ]\n"
    },
    {
      "$id": 19,
      "label": "qev092104_MSG0015",
      "style": 0,
      "name": "Shh![ST:wait ]\n"
    },
    {
      "$id": 20,
      "label": "qev092104_MSG0016",
      "style": 0,
      "name": "What's wrong?[ST:wait ]\n"
    },
    {
      "$id": 21,
      "label": "qev092104_MSG0017",
      "style": 0,
      "name": "It's a Ganglion Skell. No, more than one. Moving slow.[ST:wait ]\n"
    },
    {
      "$id": 22,
      "label": "qev092104_MSG0018",
      "style": 0,
      "name": "How do you know?[ST:wait ]\n"
    },
    {
      "$id": 23,
      "label": "qev092104_MSG0019",
      "style": 0,
      "name": "I can hear them.[ST:wait ]\n"
    },
    {
      "$id": 24,
      "label": "qev092104_MSG0020",
      "style": 0,
      "name": "You know enemy Skells by their sound? You ARE obsessed![ST:wait ]\n"
    },
    {
      "$id": 25,
      "label": "qev092104_MSG0021",
      "style": 0,
      "name": "STAY BACK![ST:wait ]\n"
    },
    {
      "$id": 26,
      "label": "qev092104_MSG0022",
      "style": 0,
      "name": "Mika?![ST:wait ]\n"
    },
    {
      "$id": 27,
      "label": "qev092104_MSG0023",
      "style": 0,
      "name": "She's still alive![ST:wait ]\n"
    },
    {
      "$id": 28,
      "label": "qev092104_MSG0024",
      "style": 0,
      "name": "We have to help her![ST:wait ]\n"
    }
  ]
}