{
  "schema": [
    {
      "name": "label",
      "type": 9
    },
    {
      "name": "style",
      "type": 2
    },
    {
      "name": "name",
      "type": 7
    }
  ],
  "rows": [
    {
      "$id": 1,
      "label": "qev041406_MSG0001",
      "style": 1,
      "name": "That massive explosion just now definitely came from the direction of Pissa's caravan, mo.[ST:wait ]"
    },
    {
      "$id": 2,
      "label": "qev041406_MSG0002",
      "style": 1,
      "name": "I thoroughly taught Potepote how to make the fireworks, though...[ST:wait ]"
    },
    {
      "$id": 3,
      "label": "qev041406_MSG0003",
      "style": 1,
      "name": "...Yes, this is Pissa, mo!\nIs that you, Potepote, mo?![ST:wait ]"
    },
    {
      "$id": 4,
      "label": "qev041406_MSG0004",
      "style": 1,
      "name": "The fireworks suddenly went BOOM, mo!\nI did exactly as you told me, so this is strange, mo! Take responsibility for this, mo![ST:wait ]"
    },
    {
      "$id": 5,
      "label": "qev041406_MSG0005",
      "style": 1,
      "name": "Umm... did you add the exact amount of autiga powder that I told you to, mo?[ST:wait ]"
    },
    {
      "$id": 6,
      "label": "qev041406_MSG0006",
      "style": 1,
      "name": "I do not have time to measure things one by one, mo.\nBut I added a whole lot of it so it would be a spectacular firework, mo.[ST:wait ]"
    },
    {
      "$id": 7,
      "label": "qev041406_MSG0007",
      "style": 1,
      "name": "......[ST:wait ]"
    },
    {
      "$id": 8,
      "label": "qev041406_MSG0008",
      "style": 1,
      "name": "More importantly, the explosion blew me away and now I am on top of a flying ship near the caravan, mo.\nHurry up and come save me, Pissa, mo.[ST:wait ]"
    },
    {
      "$id": 9,
      "label": "qev041406_MSG0009",
      "style": 1,
      "name": "...Ah, my stomach is also completely empty, so I want you to bring me some coldberries while you are at it, mo.[ST:wait ]"
    },
    {
      "$id": 10,
      "label": "qev041406_MSG0010",
      "style": 1,
      "name": "By the way, if you do not flavor them with spicy sacrifole pollen, I will absolutely not eat them, mo.[ST:wait ]"
    },
    {
      "$id": 11,
      "label": "qev041406_MSG0011",
      "style": 1,
      "name": "......[ST:wait ]"
    },
    {
      "$id": 12,
      "label": "qev041406_MSG0012",
      "style": 1,
      "name": "*Cough*... Why have you frozen up, mo?\nIf your tummy hurts, I will massage it for you, mo.[ST:wait ]"
    },
    {
      "$id": 13,
      "label": "qev041406_MSG0013",
      "style": 1,
      "name": "Gah! Do not touch me, mo![ST:wait ]"
    },
    {
      "$id": 14,
      "label": "qev041406_MSG0014",
      "style": 1,
      "name": "I am absolutely done with these people, mo!\nThat is right! Pissa is going to start a second life in this city of Earthlings, mo![ST:wait ]"
    },
    {
      "$id": 15,
      "label": "qev041406_JNK0010",
      "style": 4,
      "name": "Stop"
    },
    {
      "$id": 16,
      "label": "qev041406_SEL0011",
      "style": 3,
      "name": "Soothe the angry Pissa and stop her."
    },
    {
      "$id": 17,
      "label": "qev041406_JNK0020",
      "style": 4,
      "name": "Let her go"
    },
    {
      "$id": 18,
      "label": "qev041406_SEL0021",
      "style": 3,
      "name": "Let Pissa go just like that."
    },
    {
      "$id": 19,
      "label": "qev041406_MSG0015",
      "style": 1,
      "name": "I have reached the absolute limit of my patience, mo!\nPotepote and the Elder can both rot in hell, mo!\nNow then, farewell, mo![ST:wait ]"
    },
    {
      "$id": 20,
      "label": "qev041406_MSG0016",
      "style": 1,
      "name": "I am so glad that you at least understand me, mo!\nPotepote and the Elder can both rot in hell, mo!\nNow then, farewell, mo![ST:wait ]"
    },
    {
      "$id": 21,
      "label": "qev041406_MSG0017",
      "style": 1,
      "name": "Oh dear... She is gone, mo.[ST:wait ]"
    },
    {
      "$id": 22,
      "label": "qev041406_MSG0018",
      "style": 1,
      "name": "Well, it cannot be helped, mo.\nFor now, please go check on how Potepote is doing, mo.[ST:wait ]"
    },
    {
      "$id": 23,
      "label": "qev041406_MSG0019",
      "style": 1,
      "name": "Eeek! What wonderful clothes, mo!\nI want to try wearing something that shiny, mo![ST:wait ]"
    },
    {
      "$id": 24,
      "label": "qev041406_MSG0020",
      "style": 1,
      "name": "...Huh? Potepote? Who is that, mo?\nI do not know anyone by that name, mo.[ST:wait ]"
    }
  ]
}