{
  "schema": [
    {
      "name": "label",
      "type": 9
    },
    {
      "name": "style",
      "type": 2
    },
    {
      "name": "name",
      "type": 7
    }
  ],
  "rows": [
    {
      "$id": 1,
      "label": "xs05030100_MSG0001",
      "style": 0,
      "name": "I can't get over your cooking, Lin.\nThat was delicious![ST:wait ]\n"
    },
    {
      "$id": 2,
      "label": "xs05030100_MSG0002",
      "style": 0,
      "name": "Thanks, Gwin, glad you liked it!\nI hope it was enough?[ST:wait ]\n"
    },
    {
      "$id": 3,
      "label": "xs05030100_MSG0003",
      "style": 0,
      "name": "If I'd known we were expecting company,\nI definitely would have made more.[ST:wait ]\n"
    },
    {
      "$id": 4,
      "label": "xs05030100_MSG0004",
      "style": 0,
      "name": "Yes, yes! Then maybe Tatsu could eat full portion! Meh![ST:wait ]\n"
    },
    {
      "$id": 5,
      "label": "xs05030100_MSG0005",
      "style": 0,
      "name": "Sorry, pint-size.[ST:wait ]\n"
    },
    {
      "$id": 6,
      "label": "xs05030100_MSG0006",
      "style": 0,
      "name": "What Gwin lacks in stature, he more than makes up for\nwith his monstrous appetite. He's...kind of a pig.[ST:wait ]\n"
    },
    {
      "$id": 7,
      "label": "xs05030100_MSG0007",
      "style": 0,
      "name": "Okay, first of all? I'm taller than you![ST:wait ]\n"
    },
    {
      "$id": 8,
      "label": "xs05030100_MSG0008",
      "style": 0,
      "name": "And second, you just ate almost double what I did!\nWho's the pig here?[ST:wait ]\n"
    },
    {
      "$id": 9,
      "label": "xs05030100_MSG0009",
      "style": 0,
      "name": "I'm assuming you didn't just come here to argue?\nWhat's going on?[ST:wait ]\n"
    }
  ]
}