{
  "schema": [
    {
      "name": "label",
      "type": 9
    },
    {
      "name": "style",
      "type": 2
    },
    {
      "name": "name",
      "type": 7
    }
  ],
  "rows": [
    {
      "$id": 1,
      "label": "xs03050100_MSG0001",
      "style": 0,
      "name": "They're...all...dead. You killed them all...in cold blood...[ST:wait ]\n"
    },
    {
      "$id": 2,
      "label": "xs03050100_MSG0002",
      "style": 0,
      "name": "Fortune did not smile upon them today.[ST:wait ]\n"
    },
    {
      "$id": 3,
      "label": "xs03050100_MSG0003",
      "style": 0,
      "name": "Nelson...[ST:wait ]\n"
    },
    {
      "$id": 4,
      "label": "xs03050100_MSG0004",
      "style": 0,
      "name": "You filthy Earth aliens do not belong on this planet.[ST:wait ]\n"
    },
    {
      "$id": 5,
      "label": "xs03050100_MSG0005",
      "style": 0,
      "name": "You seem more fluent than the others.\nAre you in charge?[ST:wait ]\n"
    },
    {
      "$id": 6,
      "label": "xs03050100_MSG0006",
      "style": 0,
      "name": "I am called Glennar.[ST:wait ]\n"
    },
    {
      "$id": 7,
      "label": "xs03050100_MSG0007",
      "style": 0,
      "name": "I command this squad, Earth alien.\nNow it is time for you to surrender.[ST:wait ]\n"
    },
    {
      "$id": 8,
      "label": "xs03050100_MSG0008",
      "style": 0,
      "name": "Hello, Glennar.[ST:wait ]\n"
    },
    {
      "$id": 9,
      "label": "xs03050100_MSG0009",
      "style": 0,
      "name": "I am called Elma. And I command THIS squad.\nIf this planet is your home, we apologize for intruding.[ST:wait ]\n"
    },
    {
      "$id": 10,
      "label": "xs03050100_MSG0010",
      "style": 0,
      "name": "We crash-landed here after our ship was damaged\nin an attack by unknown adversaries.[ST:wait ]\n"
    },
    {
      "$id": 11,
      "label": "xs03050100_MSG0011",
      "style": 0,
      "name": "We were hoping we could negotiate\na peaceful settlement in exchange for our friends, but...[ST:wait ]\n"
    },
    {
      "$id": 12,
      "label": "xs03050100_MSG0012",
      "style": 0,
      "name": "Peaceful settlement?\nYour words are wasted on us.[ST:wait ]\n"
    },
    {
      "$id": 13,
      "label": "xs03050100_MSG0013",
      "style": 0,
      "name": "All we can promise Earth aliens is a swift death![ST:wait ]\n"
    },
    {
      "$id": 14,
      "label": "xs03050100_MSG0014",
      "style": 0,
      "name": "Elma...[ST:wait ]\n"
    },
    {
      "$id": 15,
      "label": "xs03050100_MSG0015",
      "style": 0,
      "name": "Right. We tried—looks like survival of the fittest it is.[ST:wait ]\n"
    },
    {
      "$id": 16,
      "label": "xs03050100_MSG0016",
      "style": 0,
      "name": "Fine then. Seeing as you know we come from Earth...[ST:wait ]\n"
    },
    {
      "$id": 17,
      "label": "xs03050100_MSG0017",
      "style": 0,
      "name": "I'm guessing there's a good chance\nwe might have a score to settle with you anyway.[ST:wait ]\n"
    }
  ]
}